Workbook

Sheet Ratios
A1: Company | B1: Years | C1: EBITDA Margin | D1: Free Cashflow | E1: Net Debt | F1: ROE | G1: Revenue Growth
A2: Sun Pharmaceutical | B2: 2022 | C2: =(('Sun Pharmaceutical '!B13+'Sun Pharmaceutical '!B19)/'Sun Pharmaceutical '!B4)*100 -> 32.084648 | D2: ='Sun Pharmaceutical '!B100 -> 7550 | E2: ='Sun Pharmaceutical '!B37-'Sun Pharmaceutical '!B64 -> -3743 | F2: =('Sun Pharmaceutical '!B22/('Sun Pharmaceutical '!B35+'Sun Pharmaceutical '!B36))*100 -> 7.058799 | G2: ='Sun Pharmaceutical '!B5 -> 0.1539
A3: Sun Pharmaceutical | B3: 2023 | C3: =(('Sun Pharmaceutical '!C13+'Sun Pharmaceutical '!C19)/'Sun Pharmaceutical '!C4)*100 -> 32.308709 | D3: ='Sun Pharmaceutical '!C100 -> 2895 | E3: ='Sun Pharmaceutical '!C37-'Sun Pharmaceutical '!C64 -> 1116 | F3: =('Sun Pharmaceutical '!C22/('Sun Pharmaceutical '!C35+'Sun Pharmaceutical '!C36))*100 -> 15.203143 | G3: ='Sun Pharmaceutical '!C5 -> 0.1353
A4: Sun Pharmaceutical | B4: 2024 | C4: =(('Sun Pharmaceutical '!D13+'Sun Pharmaceutical '!D19)/'Sun Pharmaceutical '!D4)*100 -> 32.115389 | D4: ='Sun Pharmaceutical '!D100 -> 9964 | E4: ='Sun Pharmaceutical '!D37-'Sun Pharmaceutical '!D64 -> -7247 | F4: =('Sun Pharmaceutical '!D22/('Sun Pharmaceutical '!D35+'Sun Pharmaceutical '!D36))*100 -> 15.094162 | G4: ='Sun Pharmaceutical '!D5 -> 0.1051
A5: Sun Pharmaceutical | B5: 2025 | C5: =(('Sun Pharmaceutical '!E13+'Sun Pharmaceutical '!E19)/'Sun Pharmaceutical '!E4)*100 -> 33.643349 | D5: ='Sun Pharmaceutical '!E100 -> 12005 | E5: ='Sun Pharmaceutical '!E37-'Sun Pharmaceutical '!E64 -> -8970 | F5: =('Sun Pharmaceutical '!E22/('Sun Pharmaceutical '!E35+'Sun Pharmaceutical '!E36))*100 -> 15.183195 | G5: ='Sun Pharmaceutical '!E5 -> 0.0842
A6: Sun Pharmaceutical | B6: 2026 | C6: =(('Sun Pharmaceutical '!F13+'Sun Pharmaceutical '!F19)/'Sun Pharmaceutical '!F4)*100 -> 33.250659 | D6: ='Sun Pharmaceutical '!F100 -> 8906 | E6: ='Sun Pharmaceutical '!F37-'Sun Pharmaceutical '!F64 -> -6976 | F6: =('Sun Pharmaceutical '!F22/('Sun Pharmaceutical '!F35+'Sun Pharmaceutical '!F36))*100 -> 13.771688 | G6: ='Sun Pharmaceutical '!F5 -> 0.1119
A7: Dr Reddy | B7: 2022 | C7: =(('Dr Reddy'!B11+'Dr Reddy'!B17)/'Dr Reddy'!B4)*100 -> 22.896264 | D7: ='Dr Reddy'!B96 -> 1238 | E7: ='Dr Reddy'!B35-'Dr Reddy'!B62 -> 965 | F7: =('Dr Reddy'!B20/('Dr Reddy'!B33+'Dr Reddy'!B34))*100 -> 11.357485 | G7: ='Dr Reddy'!B5 -> 0.1311
A8: Dr Reddy | B8: 2023 | C8: =(('Dr Reddy'!C11+'Dr Reddy'!C17)/'Dr Reddy'!C4)*100 -> 31.293069 | D8: ='Dr Reddy'!C96 -> 4009 | E8: ='Dr Reddy'!C35-'Dr Reddy'!C62 -> -383 | F8: =('Dr Reddy'!C20/('Dr Reddy'!C33+'Dr Reddy'!C34))*100 -> 19.354977 | G8: ='Dr Reddy'!C5 -> 0.145
A9: Dr Reddy | B9: 2024 | C9: =(('Dr Reddy'!D11+'Dr Reddy'!D17)/'Dr Reddy'!D4)*100 -> 33.568955 | D9: ='Dr Reddy'!D96 -> 1908 | E9: ='Dr Reddy'!D35-'Dr Reddy'!D62 -> 274 | F9: =('Dr Reddy'!D20/('Dr Reddy'!D33+'Dr Reddy'!D34))*100 -> 19.742337 | G9: ='Dr Reddy'!D5 -> 0.1354
A10: Dr Reddy | B10: 2025 | C10: =(('Dr Reddy'!E11+'Dr Reddy'!E17)/'Dr Reddy'!E4)*100 -> 31.402402 | D10: ='Dr Reddy'!E96 -> 1327 | E10: ='Dr Reddy'!E35-'Dr Reddy'!E62 -> 2217 | F10: =('Dr Reddy'!E20/('Dr Reddy'!E33+'Dr Reddy'!E34))*100 -> 17.064592 | G10: ='Dr Reddy'!E5 -> 0.1654
A11: Dr Reddy | B11: 2026 | C11: =(('Dr Reddy'!F11+'Dr Reddy'!F17)/'Dr Reddy'!F4)*100 -> 25.261128 | D11: ='Dr Reddy'!F96 -> 2004 | E11: ='Dr Reddy'!F35-'Dr Reddy'!F62 -> 4385 | F11: =('Dr Reddy'!F20/('Dr Reddy'!F33+'Dr Reddy'!F34))*100 -> 10.973293 | G11: ='Dr Reddy'!F5 -> 0.0324
A12: Divi's Laboratories | B12: 2022 | C12: =(('Divis Laboratories'!B11+'Divis Laboratories'!B17)/'Divis Laboratories'!B4)*100 -> 46.841518 | D12: ='Divis Laboratories'!B91 -> 1199 | E12: ='Divis Laboratories'!B33-'Divis Laboratories'!B59 -> -2815 | F12: =('Divis Laboratories'!B20/('Divis Laboratories'!B31+'Divis Laboratories'!B32))*100 -> 25.238745 | G12: ='Divis Laboratories'!B5 -> 0.2856
A13: Divi's Laboratories | B13: 2023 | C13: =(('Divis Laboratories'!C11+'Divis Laboratories'!C17)/'Divis Laboratories'!C4)*100 -> 34.925335 | D13: ='Divis Laboratories'!C91 -> 1987 | E13: ='Divis Laboratories'!C33-'Divis Laboratories'!C59 -> -4210 | F13: =('Divis Laboratories'!C20/('Divis Laboratories'!C31+'Divis Laboratories'!C32))*100 -> 14.279001 | G13: ='Divis Laboratories'!C5 -> -0.1331
A14: Divi's Laboratories | B14: 2024 | C14: =(('Divis Laboratories'!D11+'Divis Laboratories'!D17)/'Divis Laboratories'!D4)*100 -> 32.989165 | D14: ='Divis Laboratories'!D91 -> 258 | E14: ='Divis Laboratories'!D33-'Divis Laboratories'!D59 -> -3977 | F14: =('Divis Laboratories'!D20/('Divis Laboratories'!D31+'Divis Laboratories'!D32))*100 -> 11.789846 | G14: ='Divis Laboratories'!D5 -> 0.01
A15: Divi's Laboratories | B15: 2025 | C15: =(('Divis Laboratories'!E11+'Divis Laboratories'!E17)/'Divis Laboratories'!E4)*100 -> 36.057692 | D15: ='Divis Laboratories'!E91 -> 215 | E15: ='Divis Laboratories'!E33-'Divis Laboratories'!E59 -> -3711 | F15: =('Divis Laboratories'!E20/('Divis Laboratories'!E31+'Divis Laboratories'!E32))*100 -> 14.636916 | G15: ='Divis Laboratories'!E5 -> 0.1931
A16: Divi's Laboratories | B16: 2026 | C16: =(('Divis Laboratories'!F11+'Divis Laboratories'!F17)/'Divis Laboratories'!F4)*100 -> 36.979167 | D16: ='Divis Laboratories'!F91 -> 221 | E16: ='Divis Laboratories'!F33-'Divis Laboratories'!F59 -> -3407 | F16: =('Divis Laboratories'!F20/('Divis Laboratories'!F31+'Divis Laboratories'!F32))*100 -> 15.321282 | G16: ='Divis Laboratories'!F5 -> 0.1282
A17: Cipla | B17: 2022 | C17: =((Cipla!B11+Cipla!B17)/Cipla!B4)*100 -> 25.754721 | D17: =Cipla!B100 -> 2645 | E17: =Cipla!B35-Cipla!B63 -> -872 | F17: =(Cipla!B20/(Cipla!B33+Cipla!B34))*100 -> 12.221103 | G17: =Cipla!B5 -> 0.1359
A18: Cipla | B18: 2023 | C18: =((Cipla!C11+Cipla!C17)/Cipla!C4)*100 -> 27.244759 | D18: =Cipla!C100 -> 2102 | E18: =Cipla!C35-Cipla!C63 -> -762 | F18: =(Cipla!C20/(Cipla!C33+Cipla!C34))*100 -> 12.103217 | G18: =Cipla!C5 -> 0.0455
A19: Cipla | B19: 2024 | C19: =((Cipla!D11+Cipla!D17)/Cipla!D4)*100 -> 28.486071 | D19: =Cipla!D100 -> 2819 | E19: =Cipla!D35-Cipla!D63 -> -316 | F19: =(Cipla!D20/(Cipla!D33+Cipla!D34))*100 -> 15.554557 | G19: =Cipla!D5 -> 0.1328
A20: Cipla | B20: 2025 | C20: =((Cipla!E11+Cipla!E17)/Cipla!E4)*100 -> 29.893277 | D20: =Cipla!E100 -> 3490 | E20: =Cipla!E35-Cipla!E63 -> -362 | F20: =(Cipla!E20/(Cipla!E33+Cipla!E34))*100 -> 16.891069 | G20: =Cipla!E5 -> 0.0688
A21: Cipla | B21: 2026 | C21: =((Cipla!F11+Cipla!F17)/Cipla!F4)*100 -> 25.189078 | D21: =Cipla!F100 -> 928 | E21: =Cipla!F35-Cipla!F63 -> -693 | F21: =(Cipla!F20/(Cipla!F33+Cipla!F34))*100 -> 11.21631 | G21: =Cipla!F5 -> 0.0223
A22: Torrent Pharma | B22: 2022 | C22: =(('Torrent Pharma'!B12+'Torrent Pharma'!B18)/'Torrent Pharma'!B3)*100 -> 36.35402 | D22: ='Torrent Pharma'!B96 -> 1607 | E22: ='Torrent Pharma'!E35-'Torrent Pharma'!B63 -> 2799 | F22: ='Torrent Pharma'!B21/('Torrent Pharma'!B33+'Torrent Pharma'!B34)*100 -> 13.052243 | G22: ='Torrent Pharma'!B4 -> 0.0629
A23: Torrent Pharma | B23: 2023 | C23: =(('Torrent Pharma'!C12+'Torrent Pharma'!C18)/'Torrent Pharma'!C3)*100 -> 36.891892 | D23: ='Torrent Pharma'!C96 -> 1953 | E23: ='Torrent Pharma'!F35-'Torrent Pharma'!C63 -> 14455 | F23: ='Torrent Pharma'!C21/('Torrent Pharma'!C33+'Torrent Pharma'!C34)*100 -> 20.087125 | G23: ='Torrent Pharma'!C4 -> 0.1307
A24: Torrent Pharma | B24: 2024 | C24: =(('Torrent Pharma'!D12+'Torrent Pharma'!D18)/'Torrent Pharma'!D3)*100 -> 38.926174 | D24: ='Torrent Pharma'!D96 -> 2967 | E24: ='Torrent Pharma'!G35-'Torrent Pharma'!D63 -> -839 | F24: ='Torrent Pharma'!D21/('Torrent Pharma'!D33+'Torrent Pharma'!D34)*100 -> 24.154026 | G24: ='Torrent Pharma'!D4 -> 0.1151
A25: Torrent Pharma | B25: 2025 | C25: =(('Torrent Pharma'!E12+'Torrent Pharma'!E18)/'Torrent Pharma'!E3)*100 -> 39.215005 | D25: ='Torrent Pharma'!E96 -> 1991 | E25: ='Torrent Pharma'!H35-'Torrent Pharma'!E63 -> -579 | F25: ='Torrent Pharma'!E21/('Torrent Pharma'!E33+'Torrent Pharma'!E34)*100 -> 25.177866 | G25: ='Torrent Pharma'!E4 -> 0.0735
A26: Torrent Pharma | B26: 2026 | C26: =(('Torrent Pharma'!F12+'Torrent Pharma'!F18)/'Torrent Pharma'!F3)*100 -> 40.608011 | D26: ='Torrent Pharma'!F96 -> 2386 | E26: ='Torrent Pharma'!I35-'Torrent Pharma'!F63 -> -1165 | F26: ='Torrent Pharma'!F21/('Torrent Pharma'!F33+'Torrent Pharma'!F34)*100 -> 25.488794 | G26: ='Torrent Pharma'!F4 -> 0.2139
A27: Zydus Lifesciences Ltd | B27: 2022 | C27: =(('Zydus Lifesciences Ltd'!B19+'Zydus Lifesciences Ltd'!B16)/'Zydus Lifesciences Ltd'!B3)*100 -> 34.923027 | D27: ='Zydus Lifesciences Ltd'!B98 -> 1050 | E27: ='Zydus Lifesciences Ltd'!B34-'Zydus Lifesciences Ltd'!B61 -> 3114 | F27: ='Zydus Lifesciences Ltd'!B19/('Zydus Lifesciences Ltd'!B32+'Zydus Lifesciences Ltd'!B33)*100 -> 27.166304 | G27: ='Zydus Lifesciences Ltd'!B4 -> 0.0108
A28: Zydus Lifesciences Ltd | B28: 2023 | C28: =(('Zydus Lifesciences Ltd'!C19+'Zydus Lifesciences Ltd'!C16)/'Zydus Lifesciences Ltd'!C3)*100 -> 16.331148 | D28: ='Zydus Lifesciences Ltd'!C98 -> 1697 | E28: ='Zydus Lifesciences Ltd'!C34-'Zydus Lifesciences Ltd'!C61 -> 622 | F28: ='Zydus Lifesciences Ltd'!C19/('Zydus Lifesciences Ltd'!C32+'Zydus Lifesciences Ltd'!C33)*100 -> 11.943366 | G28: ='Zydus Lifesciences Ltd'!C4 -> 0.1292
A29: Zydus Lifesciences Ltd | B29: 2024 | C29: =(('Zydus Lifesciences Ltd'!D19+'Zydus Lifesciences Ltd'!D16)/'Zydus Lifesciences Ltd'!D3)*100 -> 24.233898 | D29: ='Zydus Lifesciences Ltd'!D98 -> 2345 | E29: ='Zydus Lifesciences Ltd'!D34-'Zydus Lifesciences Ltd'!D61 -> -301 | F29: ='Zydus Lifesciences Ltd'!D19/('Zydus Lifesciences Ltd'!D32+'Zydus Lifesciences Ltd'!D33)*100 -> 20.0353 | G29: ='Zydus Lifesciences Ltd'!D4 -> 0.134
A30: Zydus Lifesciences Ltd | B30: 2025 | C30: =(('Zydus Lifesciences Ltd'!E19+'Zydus Lifesciences Ltd'!E16)/'Zydus Lifesciences Ltd'!E3)*100 -> 24.046984 | D30: ='Zydus Lifesciences Ltd'!E98 -> 5139 | E30: ='Zydus Lifesciences Ltd'!E34-'Zydus Lifesciences Ltd'!E61 -> 256 | F30: ='Zydus Lifesciences Ltd'!E19/('Zydus Lifesciences Ltd'!E32+'Zydus Lifesciences Ltd'!E33)*100 -> 19.509039 | G30: ='Zydus Lifesciences Ltd'!E4 -> 0.189
A31: Zydus Lifesciences Ltd | B31: 2026 | C31: =(('Zydus Lifesciences Ltd'!F19+'Zydus Lifesciences Ltd'!F16)/'Zydus Lifesciences Ltd'!F3)*100 -> 24.060704 | D31: ='Zydus Lifesciences Ltd'!F98 -> -530 | E31: ='Zydus Lifesciences Ltd'!F34-'Zydus Lifesciences Ltd'!F61 -> 11079 | F31: ='Zydus Lifesciences Ltd'!F19/('Zydus Lifesciences Ltd'!F32+'Zydus Lifesciences Ltd'!F33)*100 -> 18.89938 | G31: ='Zydus Lifesciences Ltd'!F4 -> 0.1681
A32: Lupin | B32: 2022 | C32: =((Lupin!B19+Lupin!B16)/Lupin!B3)*100 -> 0.79853703 | D32: =Lupin!B96 -> -531 | E32: =Lupin!B34-Lupin!B61 -> 3060 | F32: =Lupin!B19/(Lupin!B32+Lupin!B33)*100 -> -12.573027 | G32: =Lupin!B4 -> 0.0819
A33: Lupin | B33: 2023 | C33: =((Lupin!C19+Lupin!C16)/Lupin!C3)*100 -> 7.985819 | D33: =Lupin!C96 -> 436 | E33: =Lupin!C34-Lupin!C61 -> 3249 | F33: =Lupin!C19/(Lupin!C32+Lupin!C33)*100 -> 3.5940634 | G33: =Lupin!C4 -> 0.0144
A34: Lupin | B34: 2024 | C34: =((Lupin!D19+Lupin!D16)/Lupin!D3)*100 -> 15.656389 | D34: =Lupin!D96 -> 2732 | E34: =Lupin!D34-Lupin!D61 -> 1719 | F34: =Lupin!D19/(Lupin!D32+Lupin!D33)*100 -> 13.547936 | G34: =Lupin!D4 -> 0.2025
A35: Lupin | B35: 2025 | C35: =((Lupin!E19+Lupin!E16)/Lupin!E3)*100 -> 19.706711 | D35: =Lupin!E96 -> 1347 | E35: =Lupin!E34-Lupin!E61 -> 2306 | F35: =Lupin!E19/(Lupin!E32+Lupin!E33)*100 -> 19.217578 | G35: =Lupin!E4 -> 0.1348
A36: Lupin | B36: 2026 | C36: =((Lupin!F19+Lupin!F16)/Lupin!F3)*100 -> 24.075399 | D36: =Lupin!F96 -> 5527 | E36: =Lupin!F34-Lupin!F61 -> 963 | F36: =Lupin!F19/(Lupin!F32+Lupin!F33)*100 -> 23.855132 | G36: =Lupin!F4 -> 0.2312
A37: Aurobindo Pharma Ltd | B37: 2022 | C37: =(('Aurobindo Pharma Ltd'!B19+'Aurobindo Pharma Ltd'!B16)/'Aurobindo Pharma Ltd'!B3)*100 -> 16.090386 | D37: ='Aurobindo Pharma Ltd'!B97 -> 2693 | E37: ='Aurobindo Pharma Ltd'!B33-'Aurobindo Pharma Ltd'!B61 -> -1339 | F37: ='Aurobindo Pharma Ltd'!B19/('Aurobindo Pharma Ltd'!B31+'Aurobindo Pharma Ltd'!B32)*100 -> 10.770671 | G37: ='Aurobindo Pharma Ltd'!B4 -> -0.0532
A38: Aurobindo Pharma Ltd | B38: 2023 | C38: =(('Aurobindo Pharma Ltd'!C19+'Aurobindo Pharma Ltd'!C16)/'Aurobindo Pharma Ltd'!C3)*100 -> 12.766043 | D38: ='Aurobindo Pharma Ltd'!C97 -> -323 | E38: ='Aurobindo Pharma Ltd'!C33-'Aurobindo Pharma Ltd'!C61 -> -798 | F38: ='Aurobindo Pharma Ltd'!C19/('Aurobindo Pharma Ltd'!C31+'Aurobindo Pharma Ltd'!C32)*100 -> 7.1833085 | G38: ='Aurobindo Pharma Ltd'!C4 -> 0.0597
A39: Aurobindo Pharma Ltd | B39: 2024 | C39: =(('Aurobindo Pharma Ltd'!D19+'Aurobindo Pharma Ltd'!D16)/'Aurobindo Pharma Ltd'!D3)*100 -> 16.174747 | D39: ='Aurobindo Pharma Ltd'!D97 -> -1067 | E39: ='Aurobindo Pharma Ltd'!D33-'Aurobindo Pharma Ltd'!D61 -> 370 | F39: ='Aurobindo Pharma Ltd'!D19/('Aurobindo Pharma Ltd'!D31+'Aurobindo Pharma Ltd'!D32)*100 -> 10.618906 | G39: ='Aurobindo Pharma Ltd'!D4 -> 0.1668
A40: Aurobindo Pharma Ltd | B40: 2025 | C40: =(('Aurobindo Pharma Ltd'!E19+'Aurobindo Pharma Ltd'!E16)/'Aurobindo Pharma Ltd'!E3)*100 -> 16.180179 | D40: ='Aurobindo Pharma Ltd'!E97 -> 1408 | E40: ='Aurobindo Pharma Ltd'!E33-'Aurobindo Pharma Ltd'!E61 -> 28 | F40: ='Aurobindo Pharma Ltd'!E19/('Aurobindo Pharma Ltd'!E31+'Aurobindo Pharma Ltd'!E32)*100 -> 10.66977 | G40: ='Aurobindo Pharma Ltd'!E4 -> 0.0939
A41: Aurobindo Pharma Ltd | B41: 2026 | C41: =(('Aurobindo Pharma Ltd'!F19+'Aurobindo Pharma Ltd'!F16)/'Aurobindo Pharma Ltd'!F3)*100 -> 15.692509 | D41: ='Aurobindo Pharma Ltd'!F97 -> 2468 | E41: ='Aurobindo Pharma Ltd'!F33-'Aurobindo Pharma Ltd'!F61 -> -1797 | F41: ='Aurobindo Pharma Ltd'!F19/('Aurobindo Pharma Ltd'!F31+'Aurobindo Pharma Ltd'!F32)*100 -> 9.2449394 | G41: ='Aurobindo Pharma Ltd'!F4 -> 0.0608
A42: Alkem Labs | B42: 2022 | C42: =('Alkem Labs'!B19+'Alkem Labs'!B16)/'Alkem Labs'!B3*100 -> 18.657137 | D42: ='Alkem Labs'!B98 -> 783 | E42: ='Alkem Labs'!B34-'Alkem Labs'!B61 -> 89 | F42: ='Alkem Labs'!B19/('Alkem Labs'!B32+'Alkem Labs'!B33)*100 -> 19.448947 | G42: ='Alkem Labs'!B4 -> 0.1996
A43: Alkem Labs | B43: 2023 | C43: =('Alkem Labs'!C19+'Alkem Labs'!C16)/'Alkem Labs'!C3*100 -> 11.354427 | D43: ='Alkem Labs'!C98 -> 1453 | E43: ='Alkem Labs'!C34-'Alkem Labs'!C61 -> -1220 | F43: ='Alkem Labs'!C19/('Alkem Labs'!C32+'Alkem Labs'!C33)*100 -> 11.133223 | G43: ='Alkem Labs'!C4 -> 0.0908
A44: Alkem Labs | B44: 2024 | C44: =('Alkem Labs'!D19+'Alkem Labs'!D16)/'Alkem Labs'!D3*100 -> 16.656141 | D44: ='Alkem Labs'!D98 -> 1761 | E44: ='Alkem Labs'!D34-'Alkem Labs'!D61 -> -161 | F44: ='Alkem Labs'!D19/('Alkem Labs'!D32+'Alkem Labs'!D33)*100 -> 17.562064 | G44: ='Alkem Labs'!D4 -> 0.0921
A45: Alkem Labs | B45: 2025 | C45: =('Alkem Labs'!E19+'Alkem Labs'!E16)/'Alkem Labs'!E3*100 -> 19.838025 | D45: ='Alkem Labs'!E98 -> 1278 | E45: ='Alkem Labs'!E34-'Alkem Labs'!E61 -> -182 | F45: ='Alkem Labs'!E19/('Alkem Labs'!E32+'Alkem Labs'!E33)*100 -> 18.481435 | G45: ='Alkem Labs'!E4 -> 0.0234
A46: Alkem Labs | B46: 2026 | C46: =('Alkem Labs'!F19+'Alkem Labs'!F16)/'Alkem Labs'!F3*100 -> 18.576672 | D46: ='Alkem Labs'!F98 -> 1476 | E46: ='Alkem Labs'!F34-'Alkem Labs'!F61 -> 314 | F46: ='Alkem Labs'!F19/('Alkem Labs'!F32+'Alkem Labs'!F33)*100 -> 17.011577 | G46: ='Alkem Labs'!F4 -> 0.1348
A47: Abbott India | B47: 2022 | C47: =('Abbott India'!B21+'Abbott India'!B18)/'Abbott India'!B3*100 -> 17.584875 | D47: ='Abbott India'!B85 -> 904 | E47: ='Abbott India'!B34-'Abbott India'!B57 -> -2597 | F47: ='Abbott India'!B21/('Abbott India'!B32+'Abbott India'!B33)*100 -> 28.333333 | G47: ='Abbott India'!B4 -> 0.1414
A48: Abbott India | B48: 2023 | C48: =('Abbott India'!C21+'Abbott India'!C18)/'Abbott India'!C3*100 -> 19.05029 | D48: ='Abbott India'!C85 -> 860 | E48: ='Abbott India'!C34-'Abbott India'!C57 -> -1824 | F48: ='Abbott India'!C21/('Abbott India'!C32+'Abbott India'!C33)*100 -> 29.76788 | G48: ='Abbott India'!C4 -> 0.0873
A49: Abbott India | B49: 2024 | C49: =('Abbott India'!D21+'Abbott India'!D18)/'Abbott India'!D3*100 -> 21.747307 | D49: ='Abbott India'!D85 -> 1165 | E49: ='Abbott India'!D34-'Abbott India'!D57 -> -2051 | F49: ='Abbott India'!D21/('Abbott India'!D32+'Abbott India'!D33)*100 -> 32.468235 | G49: ='Abbott India'!D4 -> 0.0935
A50: Abbott India | B50: 2025 | C50: =('Abbott India'!E21+'Abbott India'!E18)/'Abbott India'!E3*100 -> 23.186144 | D50: ='Abbott India'!E85 -> 960 | E50: ='Abbott India'!E34-'Abbott India'!E57 -> -1429 | F50: ='Abbott India'!E21/('Abbott India'!E32+'Abbott India'!E33)*100 -> 33.404205 | G50: ='Abbott India'!E4 -> 0.0958
A51: Abbott India | B51: 2026 | C51: =('Abbott India'!F21+'Abbott India'!F18)/'Abbott India'!F3*100 -> 23.495454 | D51: ='Abbott India'!F85 -> 1307 | E51: ='Abbott India'!F34-'Abbott India'!F57 -> -2083 | F51: ='Abbott India'!F21/('Abbott India'!F32+'Abbott India'!F33)*100 -> 32.509426 | G51: ='Abbott India'!F4 -> 0.0811

Sheet Return
A1: Date | B1: ABBOTINDIA | C1: ALKEM | D1: AUROPHARMA | E1: LUPIN | F1: ZYDUSLIFE | G1: TORNTPHARM | H1: DRREDDY | I1: SUNPHARMA | J1: CIPLA | K1: DIVISLAB | L1: Portfolio Return | M1: SBI Net Asset Value | N1: Nippon Net Asset Value | O1: Return of SBI | P1: Return of Nippon | Q1: Portfolio 2 Return | R1: Portfolio 3 Return | S1: Portfolio 4 Return (SBI/Nippon Blend)
A2: 46080 | B2: 0.0066 | C2: -0.019558414 | D2: -0.00024576063 | E2: -0.01206 | F2: -0.017900906 | G2: -0.015114323 | H2: -0.025013265 | I2: -0.027272218 | J2: -0.0072895958 | K2: -0.010117393 | L2: =IFERROR(B2*'Stock Statistics'!$C$41+C2*'Stock Statistics'!$C$42+D2*'Stock Statistics'!$C$43+E2*'Stock Statistics'!$C$44+F2*'Stock Statistics'!$C$45+G2*'Stock Statistics'!$C$46+H2*'Stock Statistics'!$C$47+I2*'Stock Statistics'!$C$48+J2*'Stock Statistics'!$C$49+K2*'Stock Statistics'!$C$50,"") -> -0.012797188 | M2: 497.1341 | N2: 576.9248 | O2: =M2/M3-1 -> -0.010177489 | P2: =N2/N3-1 -> -0.0088691148 | Q2: =B2*'Portfolio 2 & 3'!$F$7+C2*'Portfolio 2 & 3'!$F$8+D2*'Portfolio 2 & 3'!$F$9+E2*'Portfolio 2 & 3'!$F$10+F2*'Portfolio 2 & 3'!$F$11+G2*'Portfolio 2 & 3'!$F$12+H2*'Portfolio 2 & 3'!$F$13+I2*'Portfolio 2 & 3'!$F$14+J2*'Portfolio 2 & 3'!$F$15+K2*'Portfolio 2 & 3'!$F$16 -> -0.013299705 | R2: =B2*'Portfolio 2 & 3'!$B$23+C2*'Portfolio 2 & 3'!$B$24+D2*'Portfolio 2 & 3'!$B$25+E2*'Portfolio 2 & 3'!$B$26+F2*'Portfolio 2 & 3'!$B$27+G2*'Portfolio 2 & 3'!$B$28+H2*'Portfolio 2 & 3'!$B$29+I2*'Portfolio 2 & 3'!$B$30+J2*'Portfolio 2 & 3'!$B$31+K2*'Portfolio 2 & 3'!$B$32 -> -0.015965014 | S2: =IFERROR(AVERAGE(O2,P2),"") -> -0.0095233018
A3: 46079 | B3: -0.0021 | C3: 0.022577778 | D3: 0.0075938919 | E3: 0.01352 | F3: 0.020496928 | G3: -0.0043223427 | H3: 0.009797168 | I3: 0.012186827 | J3: 0.0089146423 | K3: 0.012274255 | L3: =IFERROR(B3*'Stock Statistics'!$C$41+C3*'Stock Statistics'!$C$42+D3*'Stock Statistics'!$C$43+E3*'Stock Statistics'!$C$44+F3*'Stock Statistics'!$C$45+G3*'Stock Statistics'!$C$46+H3*'Stock Statistics'!$C$47+I3*'Stock Statistics'!$C$48+J3*'Stock Statistics'!$C$49+K3*'Stock Statistics'!$C$50,"") -> 0.010093915 | M3: 502.2457 | N3: 582.0874 | O3: =M3/M4-1 -> 0.011710969 | P3: =N3/N4-1 -> 0.0078702501 | Q3: =B3*'Portfolio 2 & 3'!$F$7+C3*'Portfolio 2 & 3'!$F$8+D3*'Portfolio 2 & 3'!$F$9+E3*'Portfolio 2 & 3'!$F$10+F3*'Portfolio 2 & 3'!$F$11+G3*'Portfolio 2 & 3'!$F$12+H3*'Portfolio 2 & 3'!$F$13+I3*'Portfolio 2 & 3'!$F$14+J3*'Portfolio 2 & 3'!$F$15+K3*'Portfolio 2 & 3'!$F$16 -> 0.010822137 | R3: =B3*'Portfolio 2 & 3'!$B$23+C3*'Portfolio 2 & 3'!$B$24+D3*'Portfolio 2 & 3'!$B$25+E3*'Portfolio 2 & 3'!$B$26+F3*'Portfolio 2 & 3'!$B$27+G3*'Portfolio 2 & 3'!$B$28+H3*'Portfolio 2 & 3'!$B$29+I3*'Portfolio 2 & 3'!$B$30+J3*'Portfolio 2 & 3'!$B$31+K3*'Portfolio 2 & 3'!$B$32 -> 0.01159166 | S3: =IFERROR(AVERAGE(O3,P3),"") -> 0.0097906098
A4: 46078 | B4: 0.0017 | C4: 0.023564735 | D4: 0.040450017 | E4: 0.01103 | F4: 0.017480777 | G4: 0.0047750063 | H4: 0.0048454084 | I4: 0.018708858 | J4: 0.014622748 | K4: 0.022380305 | L4: =IFERROR(B4*'Stock Statistics'!$C$41+C4*'Stock Statistics'!$C$42+D4*'Stock Statistics'!$C$43+E4*'Stock Statistics'!$C$44+F4*'Stock Statistics'!$C$45+G4*'Stock Statistics'!$C$46+H4*'Stock Statistics'!$C$47+I4*'Stock Statistics'!$C$48+J4*'Stock Statistics'!$C$49+K4*'Stock Statistics'!$C$50,"") -> 0.015955785 | M4: 496.432 | N4: 577.542 | O4: =M4/M5-1 -> 0.014566179 | P4: =N4/N5-1 -> 0.013631875 | Q4: =B4*'Portfolio 2 & 3'!$F$7+C4*'Portfolio 2 & 3'!$F$8+D4*'Portfolio 2 & 3'!$F$9+E4*'Portfolio 2 & 3'!$F$10+F4*'Portfolio 2 & 3'!$F$11+G4*'Portfolio 2 & 3'!$F$12+H4*'Portfolio 2 & 3'!$F$13+I4*'Portfolio 2 & 3'!$F$14+J4*'Portfolio 2 & 3'!$F$15+K4*'Portfolio 2 & 3'!$F$16 -> 0.016925966 | R4: =B4*'Portfolio 2 & 3'!$B$23+C4*'Portfolio 2 & 3'!$B$24+D4*'Portfolio 2 & 3'!$B$25+E4*'Portfolio 2 & 3'!$B$26+F4*'Portfolio 2 & 3'!$B$27+G4*'Portfolio 2 & 3'!$B$28+H4*'Portfolio 2 & 3'!$B$29+I4*'Portfolio 2 & 3'!$B$30+J4*'Portfolio 2 & 3'!$B$31+K4*'Portfolio 2 & 3'!$B$32 -> 0.015724575 | S4: =IFERROR(AVERAGE(O4,P4),"") -> 0.014099027
A5: 46077 | B5: -0.004 | C5: 0.00091066387 | D5: 0.011993742 | E5: -0.00102 | F5: -0.0045156672 | G5: 0.020962949 | H5: -0.0055071134 | I5: -0.00028863361 | J5: 0.00015077271 | K5: -0.0060379757 | L5: =IFERROR(B5*'Stock Statistics'!$C$41+C5*'Stock Statistics'!$C$42+D5*'Stock Statistics'!$C$43+E5*'Stock Statistics'!$C$44+F5*'Stock Statistics'!$C$45+G5*'Stock Statistics'!$C$46+H5*'Stock Statistics'!$C$47+I5*'Stock Statistics'!$C$48+J5*'Stock Statistics'!$C$49+K5*'Stock Statistics'!$C$50,"") -> 0.0012648738 | M5: 489.3047 | N5: 569.7749 | O5: =M5/M6-1 -> 0.0027319213 | P5: =N5/N6-1 -> -0.0023754595 | Q5: =B5*'Portfolio 2 & 3'!$F$7+C5*'Portfolio 2 & 3'!$F$8+D5*'Portfolio 2 & 3'!$F$9+E5*'Portfolio 2 & 3'!$F$10+F5*'Portfolio 2 & 3'!$F$11+G5*'Portfolio 2 & 3'!$F$12+H5*'Portfolio 2 & 3'!$F$13+I5*'Portfolio 2 & 3'!$F$14+J5*'Portfolio 2 & 3'!$F$15+K5*'Portfolio 2 & 3'!$F$16 -> 0.00064536416 | R5: =B5*'Portfolio 2 & 3'!$B$23+C5*'Portfolio 2 & 3'!$B$24+D5*'Portfolio 2 & 3'!$B$25+E5*'Portfolio 2 & 3'!$B$26+F5*'Portfolio 2 & 3'!$B$27+G5*'Portfolio 2 & 3'!$B$28+H5*'Portfolio 2 & 3'!$B$29+I5*'Portfolio 2 & 3'!$B$30+J5*'Portfolio 2 & 3'!$B$31+K5*'Portfolio 2 & 3'!$B$32 -> 0.00055071234 | S5: =IFERROR(AVERAGE(O5,P5),"") -> 0.00017823088
A6: 46076 | B6: 0.0067 | C6: 0.018267804 | D6: -0.0070762858 | E6: 0.00964 | F6: 0.0079933389 | G6: 0.015536224 | H6: 0.02108716 | I6: 0.0045813036 | J6: -0.010886586 | K6: 0.0003973931 | L6: =IFERROR(B6*'Stock Statistics'!$C$41+C6*'Stock Statistics'!$C$42+D6*'Stock Statistics'!$C$43+E6*'Stock Statistics'!$C$44+F6*'Stock Statistics'!$C$45+G6*'Stock Statistics'!$C$46+H6*'Stock Statistics'!$C$47+I6*'Stock Statistics'!$C$48+J6*'Stock Statistics'!$C$49+K6*'Stock Statistics'!$C$50,"") -> 0.0066240352 | M6: 487.9716 | N6: 571.1316 | O6: =M6/M7-1 -> 0.006126388 | P6: =N6/N7-1 -> 0.0081770622 | Q6: =B6*'Portfolio 2 & 3'!$F$7+C6*'Portfolio 2 & 3'!$F$8+D6*'Portfolio 2 & 3'!$F$9+E6*'Portfolio 2 & 3'!$F$10+F6*'Portfolio 2 & 3'!$F$11+G6*'Portfolio 2 & 3'!$F$12+H6*'Portfolio 2 & 3'!$F$13+I6*'Portfolio 2 & 3'!$F$14+J6*'Portfolio 2 & 3'!$F$15+K6*'Portfolio 2 & 3'!$F$16 -> 0.005933812 | R6: =B6*'Portfolio 2 & 3'!$B$23+C6*'Portfolio 2 & 3'!$B$24+D6*'Portfolio 2 & 3'!$B$25+E6*'Portfolio 2 & 3'!$B$26+F6*'Portfolio 2 & 3'!$B$27+G6*'Portfolio 2 & 3'!$B$28+H6*'Portfolio 2 & 3'!$B$29+I6*'Portfolio 2 & 3'!$B$30+J6*'Portfolio 2 & 3'!$B$31+K6*'Portfolio 2 & 3'!$B$32 -> 0.0086659228 | S6: =IFERROR(AVERAGE(O6,P6),"") -> 0.0071517251
A7: 46073 | B7: -0.0038 | C7: 0.0027896597 | D7: -0.01075636 | E7: 0.00063 | F7: -0.0018284574 | G7: 0.0036201022 | H7: -0.0014817125 | I7: 0.0064199837 | J7: 0.0091805252 | K7: -0.0010321556 | L7: =IFERROR(B7*'Stock Statistics'!$C$41+C7*'Stock Statistics'!$C$42+D7*'Stock Statistics'!$C$43+E7*'Stock Statistics'!$C$44+F7*'Stock Statistics'!$C$45+G7*'Stock Statistics'!$C$46+H7*'Stock Statistics'!$C$47+I7*'Stock Statistics'!$C$48+J7*'Stock Statistics'!$C$49+K7*'Stock Statistics'!$C$50,"") -> 0.00037415853 | M7: 485.0003 | N7: 566.4993 | O7: =M7/M8-1 -> -0.0017318398 | P7: =N7/N8-1 -> -0.00026136183 | Q7: =B7*'Portfolio 2 & 3'!$F$7+C7*'Portfolio 2 & 3'!$F$8+D7*'Portfolio 2 & 3'!$F$9+E7*'Portfolio 2 & 3'!$F$10+F7*'Portfolio 2 & 3'!$F$11+G7*'Portfolio 2 & 3'!$F$12+H7*'Portfolio 2 & 3'!$F$13+I7*'Portfolio 2 & 3'!$F$14+J7*'Portfolio 2 & 3'!$F$15+K7*'Portfolio 2 & 3'!$F$16 -> 0.00019418118 | R7: =B7*'Portfolio 2 & 3'!$B$23+C7*'Portfolio 2 & 3'!$B$24+D7*'Portfolio 2 & 3'!$B$25+E7*'Portfolio 2 & 3'!$B$26+F7*'Portfolio 2 & 3'!$B$27+G7*'Portfolio 2 & 3'!$B$28+H7*'Portfolio 2 & 3'!$B$29+I7*'Portfolio 2 & 3'!$B$30+J7*'Portfolio 2 & 3'!$B$31+K7*'Portfolio 2 & 3'!$B$32 -> 0.0017615928 | S7: =IFERROR(AVERAGE(O7,P7),"") -> -0.00099660082
A8: 46072 | B8: -0.0025 | C8: -0.015922401 | D8: 0.010175923 | E8: -0.00237 | F8: -0.0084061315 | G8: 0.0037047592 | H8: 0.0015621339 | I8: -0.0063790304 | J8: -0.015483775 | K8: 0.0022280576 | L8: =IFERROR(B8*'Stock Statistics'!$C$41+C8*'Stock Statistics'!$C$42+D8*'Stock Statistics'!$C$43+E8*'Stock Statistics'!$C$44+F8*'Stock Statistics'!$C$45+G8*'Stock Statistics'!$C$46+H8*'Stock Statistics'!$C$47+I8*'Stock Statistics'!$C$48+J8*'Stock Statistics'!$C$49+K8*'Stock Statistics'!$C$50,"") -> -0.0033390465 | M8: 485.8417 | N8: 566.6474 | O8: =M8/M9-1 -> -0.0061605394 | P8: =N8/N9-1 -> -0.0053610522 | Q8: =B8*'Portfolio 2 & 3'!$F$7+C8*'Portfolio 2 & 3'!$F$8+D8*'Portfolio 2 & 3'!$F$9+E8*'Portfolio 2 & 3'!$F$10+F8*'Portfolio 2 & 3'!$F$11+G8*'Portfolio 2 & 3'!$F$12+H8*'Portfolio 2 & 3'!$F$13+I8*'Portfolio 2 & 3'!$F$14+J8*'Portfolio 2 & 3'!$F$15+K8*'Portfolio 2 & 3'!$F$16 -> -0.0035525103 | R8: =B8*'Portfolio 2 & 3'!$B$23+C8*'Portfolio 2 & 3'!$B$24+D8*'Portfolio 2 & 3'!$B$25+E8*'Portfolio 2 & 3'!$B$26+F8*'Portfolio 2 & 3'!$B$27+G8*'Portfolio 2 & 3'!$B$28+H8*'Portfolio 2 & 3'!$B$29+I8*'Portfolio 2 & 3'!$B$30+J8*'Portfolio 2 & 3'!$B$31+K8*'Portfolio 2 & 3'!$B$32 -> -0.0060508028 | S8: =IFERROR(AVERAGE(O8,P8),"") -> -0.0057607958
A9: 46071 | B9: -0.006 | C9: 0.0013745075 | D9: -0.022836437 | E9: -0.01255 | F9: 0.0037500689 | G9: -0.011177907 | H9: -0.0035024907 | I9: 0.004251354 | J9: 0.0043902076 | K9: 0.015515152 | L9: =IFERROR(B9*'Stock Statistics'!$C$41+C9*'Stock Statistics'!$C$42+D9*'Stock Statistics'!$C$43+E9*'Stock Statistics'!$C$44+F9*'Stock Statistics'!$C$45+G9*'Stock Statistics'!$C$46+H9*'Stock Statistics'!$C$47+I9*'Stock Statistics'!$C$48+J9*'Stock Statistics'!$C$49+K9*'Stock Statistics'!$C$50,"") -> -0.0026785545 | M9: 488.8533 | N9: 569.7016 | O9: =M9/M10-1 -> 0.0050751997 | P9: =N9/N10-1 -> 8.3559494e-05 | Q9: =B9*'Portfolio 2 & 3'!$F$7+C9*'Portfolio 2 & 3'!$F$8+D9*'Portfolio 2 & 3'!$F$9+E9*'Portfolio 2 & 3'!$F$10+F9*'Portfolio 2 & 3'!$F$11+G9*'Portfolio 2 & 3'!$F$12+H9*'Portfolio 2 & 3'!$F$13+I9*'Portfolio 2 & 3'!$F$14+J9*'Portfolio 2 & 3'!$F$15+K9*'Portfolio 2 & 3'!$F$16 -> -0.0027990656 | R9: =B9*'Portfolio 2 & 3'!$B$23+C9*'Portfolio 2 & 3'!$B$24+D9*'Portfolio 2 & 3'!$B$25+E9*'Portfolio 2 & 3'!$B$26+F9*'Portfolio 2 & 3'!$B$27+G9*'Portfolio 2 & 3'!$B$28+H9*'Portfolio 2 & 3'!$B$29+I9*'Portfolio 2 & 3'!$B$30+J9*'Portfolio 2 & 3'!$B$31+K9*'Portfolio 2 & 3'!$B$32 -> 0.0010160793 | S9: =IFERROR(AVERAGE(O9,P9),"") -> 0.0025793796
A10: 46070 | B10: 0.0126 | C10: -0.0043791625 | D10: 0.0017727503 | E10: 0.00559 | F10: -0.0041737602 | G10: -0.00072744339 | H10: 0.012131716 | I10: 0.0097618348 | J10: -0.0092155706 | K10: 0.0061793642 | L10: =IFERROR(B10*'Stock Statistics'!$C$41+C10*'Stock Statistics'!$C$42+D10*'Stock Statistics'!$C$43+E10*'Stock Statistics'!$C$44+F10*'Stock Statistics'!$C$45+G10*'Stock Statistics'!$C$46+H10*'Stock Statistics'!$C$47+I10*'Stock Statistics'!$C$48+J10*'Stock Statistics'!$C$49+K10*'Stock Statistics'!$C$50,"") -> 0.0029539728 | M10: 486.3848 | N10: 569.654 | O10: =M10/M11-1 -> 0.0064350538 | P10: =N10/N11-1 -> 0.0050446837 | Q10: =B10*'Portfolio 2 & 3'!$F$7+C10*'Portfolio 2 & 3'!$F$8+D10*'Portfolio 2 & 3'!$F$9+E10*'Portfolio 2 & 3'!$F$10+F10*'Portfolio 2 & 3'!$F$11+G10*'Portfolio 2 & 3'!$F$12+H10*'Portfolio 2 & 3'!$F$13+I10*'Portfolio 2 & 3'!$F$14+J10*'Portfolio 2 & 3'!$F$15+K10*'Portfolio 2 & 3'!$F$16 -> 0.0025484427 | R10: =B10*'Portfolio 2 & 3'!$B$23+C10*'Portfolio 2 & 3'!$B$24+D10*'Portfolio 2 & 3'!$B$25+E10*'Portfolio 2 & 3'!$B$26+F10*'Portfolio 2 & 3'!$B$27+G10*'Portfolio 2 & 3'!$B$28+H10*'Portfolio 2 & 3'!$B$29+I10*'Portfolio 2 & 3'!$B$30+J10*'Portfolio 2 & 3'!$B$31+K10*'Portfolio 2 & 3'!$B$32 -> 0.003167135 | S10: =IFERROR(AVERAGE(O10,P10),"") -> 0.0057398688
A11: 46069 | B11: -0.0064 | C11: 0.01443776 | D11: 0.034043296 | E11: 0.00099 | F11: 0.006355698 | G11: 0.044997548 | H11: 0.0010251557 | I11: 0.0017673049 | J11: 0.018700713 | K11: -0.0030801654 | L11: =IFERROR(B11*'Stock Statistics'!$C$41+C11*'Stock Statistics'!$C$42+D11*'Stock Statistics'!$C$43+E11*'Stock Statistics'!$C$44+F11*'Stock Statistics'!$C$45+G11*'Stock Statistics'!$C$46+H11*'Stock Statistics'!$C$47+I11*'Stock Statistics'!$C$48+J11*'Stock Statistics'!$C$49+K11*'Stock Statistics'!$C$50,"") -> 0.011283731 | M11: 483.2749 | N11: 566.7947 | O11: =M11/M12-1 -> 0.0049656156 | P11: =N11/N12-1 -> 0.0073962917 | Q11: =B11*'Portfolio 2 & 3'!$F$7+C11*'Portfolio 2 & 3'!$F$8+D11*'Portfolio 2 & 3'!$F$9+E11*'Portfolio 2 & 3'!$F$10+F11*'Portfolio 2 & 3'!$F$11+G11*'Portfolio 2 & 3'!$F$12+H11*'Portfolio 2 & 3'!$F$13+I11*'Portfolio 2 & 3'!$F$14+J11*'Portfolio 2 & 3'!$F$15+K11*'Portfolio 2 & 3'!$F$16 -> 0.011488836 | R11: =B11*'Portfolio 2 & 3'!$B$23+C11*'Portfolio 2 & 3'!$B$24+D11*'Portfolio 2 & 3'!$B$25+E11*'Portfolio 2 & 3'!$B$26+F11*'Portfolio 2 & 3'!$B$27+G11*'Portfolio 2 & 3'!$B$28+H11*'Portfolio 2 & 3'!$B$29+I11*'Portfolio 2 & 3'!$B$30+J11*'Portfolio 2 & 3'!$B$31+K11*'Portfolio 2 & 3'!$B$32 -> 0.008930598 | S11: =IFERROR(AVERAGE(O11,P11),"") -> 0.0061809537
A12: 46066 | B12: -0.0075 | C12: -0.079720637 | D12: -0.010622679 | E12: -0.00484 | F12: -0.017644823 | G12: 0.00019621309 | H12: -0.0053337517 | I12: -0.010146364 | J12: 0.0011278195 | K12: -0.0026677445 | L12: =IFERROR(B12*'Stock Statistics'!$C$41+C12*'Stock Statistics'!$C$42+D12*'Stock Statistics'!$C$43+E12*'Stock Statistics'!$C$44+F12*'Stock Statistics'!$C$45+G12*'Stock Statistics'!$C$46+H12*'Stock Statistics'!$C$47+I12*'Stock Statistics'!$C$48+J12*'Stock Statistics'!$C$49+K12*'Stock Statistics'!$C$50,"") -> -0.013715197 | M12: 480.887 | N12: 562.6333 | O12: =M12/M13-1 -> -0.010106899 | P12: =N12/N13-1 -> -0.0079195986 | Q12: =B12*'Portfolio 2 & 3'!$F$7+C12*'Portfolio 2 & 3'!$F$8+D12*'Portfolio 2 & 3'!$F$9+E12*'Portfolio 2 & 3'!$F$10+F12*'Portfolio 2 & 3'!$F$11+G12*'Portfolio 2 & 3'!$F$12+H12*'Portfolio 2 & 3'!$F$13+I12*'Portfolio 2 & 3'!$F$14+J12*'Portfolio 2 & 3'!$F$15+K12*'Portfolio 2 & 3'!$F$16 -> -0.013585931 | R12: =B12*'Portfolio 2 & 3'!$B$23+C12*'Portfolio 2 & 3'!$B$24+D12*'Portfolio 2 & 3'!$B$25+E12*'Portfolio 2 & 3'!$B$26+F12*'Portfolio 2 & 3'!$B$27+G12*'Portfolio 2 & 3'!$B$28+H12*'Portfolio 2 & 3'!$B$29+I12*'Portfolio 2 & 3'!$B$30+J12*'Portfolio 2 & 3'!$B$31+K12*'Portfolio 2 & 3'!$B$32 -> -0.022028215 | S12: =IFERROR(AVERAGE(O12,P12),"") -> -0.0090132486
A13: 46065 | B13: -0.0095 | C13: -0.0033106961 | D13: 0.0098552241 | E13: -0.00311 | F13: 0.025214294 | G13: 0.0050533685 | H13: 0.0036211918 | I13: 0.0022207936 | J13: -0.014741833 | K13: -0.031550928 | L13: =IFERROR(B13*'Stock Statistics'!$C$41+C13*'Stock Statistics'!$C$42+D13*'Stock Statistics'!$C$43+E13*'Stock Statistics'!$C$44+F13*'Stock Statistics'!$C$45+G13*'Stock Statistics'!$C$46+H13*'Stock Statistics'!$C$47+I13*'Stock Statistics'!$C$48+J13*'Stock Statistics'!$C$49+K13*'Stock Statistics'!$C$50,"") -> -0.0016248585 | M13: 485.7969 | N13: 567.1247 | O13: =M13/M14-1 -> -0.0032031894 | P13: =N13/N14-1 -> -0.0061762989 | Q13: =B13*'Portfolio 2 & 3'!$F$7+C13*'Portfolio 2 & 3'!$F$8+D13*'Portfolio 2 & 3'!$F$9+E13*'Portfolio 2 & 3'!$F$10+F13*'Portfolio 2 & 3'!$F$11+G13*'Portfolio 2 & 3'!$F$12+H13*'Portfolio 2 & 3'!$F$13+I13*'Portfolio 2 & 3'!$F$14+J13*'Portfolio 2 & 3'!$F$15+K13*'Portfolio 2 & 3'!$F$16 -> -0.00084215547 | R13: =B13*'Portfolio 2 & 3'!$B$23+C13*'Portfolio 2 & 3'!$B$24+D13*'Portfolio 2 & 3'!$B$25+E13*'Portfolio 2 & 3'!$B$26+F13*'Portfolio 2 & 3'!$B$27+G13*'Portfolio 2 & 3'!$B$28+H13*'Portfolio 2 & 3'!$B$29+I13*'Portfolio 2 & 3'!$B$30+J13*'Portfolio 2 & 3'!$B$31+K13*'Portfolio 2 & 3'!$B$32 -> 0.00019966471 | S13: =IFERROR(AVERAGE(O13,P13),"") -> -0.0046897441
... A1210: 44306 | B1210: 0.0078 | C1210: -0.010114729 | D1210: -0.012645161 | E1210: 0.00454 | F1210: 0.055202504 | G1210: 0.0068944904 | H1210: 0.0044256358 | I1210: -0.016219677 | J1210: 0.011611361 | K1210: -0.021759941 | L1210: =IFERROR(B1210*'Stock Statistics'!$C$41+C1210*'Stock Statistics'!$C$42+D1210*'Stock Statistics'!$C$43+E1210*'Stock Statistics'!$C$44+F1210*'Stock Statistics'!$C$45+G1210*'Stock Statistics'!$C$46+H1210*'Stock Statistics'!$C$47+I1210*'Stock Statistics'!$C$48+J1210*'Stock Statistics'!$C$49+K1210*'Stock Statistics'!$C$50,"") -> 0.0029734483 | M1210: 226.3497 | N1210: 276.3479 | O1210: =M1210/M1211-1 -> 0.017965873 | P1210: =N1210/N1211-1 -> 0.01175638 | Q1210: =B1210*'Portfolio 2 & 3'!$F$7+C1210*'Portfolio 2 & 3'!$F$8+D1210*'Portfolio 2 & 3'!$F$9+E1210*'Portfolio 2 & 3'!$F$10+F1210*'Portfolio 2 & 3'!$F$11+G1210*'Portfolio 2 & 3'!$F$12+H1210*'Portfolio 2 & 3'!$F$13+I1210*'Portfolio 2 & 3'!$F$14+J1210*'Portfolio 2 & 3'!$F$15+K1210*'Portfolio 2 & 3'!$F$16 -> 0.0035694175 | R1210: =B1210*'Portfolio 2 & 3'!$B$23+C1210*'Portfolio 2 & 3'!$B$24+D1210*'Portfolio 2 & 3'!$B$25+E1210*'Portfolio 2 & 3'!$B$26+F1210*'Portfolio 2 & 3'!$B$27+G1210*'Portfolio 2 & 3'!$B$28+H1210*'Portfolio 2 & 3'!$B$29+I1210*'Portfolio 2 & 3'!$B$30+J1210*'Portfolio 2 & 3'!$B$31+K1210*'Portfolio 2 & 3'!$B$32 -> 0.0029812182 | S1210: =IFERROR(AVERAGE(O1210,P1210),"") -> 0.014861127
A1211: 44305 | B1211: -0.016 | C1211: 0.0070003059 | D1211: -0.012336239 | E1211: 0.02344 | F1211: 9.4858661e-05 | G1211: 0.0035193665 | H1211: 0.011916195 | I1211: -0.007414207 | J1211: -0.034882443 | K1211: 0.0028677982 | L1211: =IFERROR(B1211*'Stock Statistics'!$C$41+C1211*'Stock Statistics'!$C$42+D1211*'Stock Statistics'!$C$43+E1211*'Stock Statistics'!$C$44+F1211*'Stock Statistics'!$C$45+G1211*'Stock Statistics'!$C$46+H1211*'Stock Statistics'!$C$47+I1211*'Stock Statistics'!$C$48+J1211*'Stock Statistics'!$C$49+K1211*'Stock Statistics'!$C$50,"") -> -0.0021794365 | M1211: 222.3549 | N1211: 273.1368 | O1211: =M1211/M1213-1 -> 0.0081374646 | P1211: =N1211/N1213-1 -> 0.0091200189 | Q1211: =B1211*'Portfolio 2 & 3'!$F$7+C1211*'Portfolio 2 & 3'!$F$8+D1211*'Portfolio 2 & 3'!$F$9+E1211*'Portfolio 2 & 3'!$F$10+F1211*'Portfolio 2 & 3'!$F$11+G1211*'Portfolio 2 & 3'!$F$12+H1211*'Portfolio 2 & 3'!$F$13+I1211*'Portfolio 2 & 3'!$F$14+J1211*'Portfolio 2 & 3'!$F$15+K1211*'Portfolio 2 & 3'!$F$16 -> -0.0036532386 | R1211: =B1211*'Portfolio 2 & 3'!$B$23+C1211*'Portfolio 2 & 3'!$B$24+D1211*'Portfolio 2 & 3'!$B$25+E1211*'Portfolio 2 & 3'!$B$26+F1211*'Portfolio 2 & 3'!$B$27+G1211*'Portfolio 2 & 3'!$B$28+H1211*'Portfolio 2 & 3'!$B$29+I1211*'Portfolio 2 & 3'!$B$30+J1211*'Portfolio 2 & 3'!$B$31+K1211*'Portfolio 2 & 3'!$B$32 -> -0.0029639494 | S1211: =IFERROR(AVERAGE(O1211,P1211),"") -> 0.0086287417
H1212: 0.011468049 | Q1212: =B1212*'Portfolio 2 & 3'!$F$7+C1212*'Portfolio 2 & 3'!$F$8+D1212*'Portfolio 2 & 3'!$F$9+E1212*'Portfolio 2 & 3'!$F$10+F1212*'Portfolio 2 & 3'!$F$11+G1212*'Portfolio 2 & 3'!$F$12+H1212*'Portfolio 2 & 3'!$F$13+I1212*'Portfolio 2 & 3'!$F$14+J1212*'Portfolio 2 & 3'!$F$15+K1212*'Portfolio 2 & 3'!$F$16 -> 0.0018765898 | R1212: =B1212*'Portfolio 2 & 3'!$B$23+C1212*'Portfolio 2 & 3'!$B$24+D1212*'Portfolio 2 & 3'!$B$25+E1212*'Portfolio 2 & 3'!$B$26+F1212*'Portfolio 2 & 3'!$B$27+G1212*'Portfolio 2 & 3'!$B$28+H1212*'Portfolio 2 & 3'!$B$29+I1212*'Portfolio 2 & 3'!$B$30+J1212*'Portfolio 2 & 3'!$B$31+K1212*'Portfolio 2 & 3'!$B$32 -> 0.00034404147
A1213: 44302 | B1213: 0.003 | C1213: -0.0067563944 | D1213: 0.014112903 | E1213: -0.00425 | F1213: 0.044382802 | G1213: -0.00073931983 | H1213: -0.0025310198 | I1213: 0.014179318 | J1213: -0.00016477179 | K1213: 0.038738382 | L1213: =IFERROR(B1213*'Stock Statistics'!$C$41+C1213*'Stock Statistics'!$C$42+D1213*'Stock Statistics'!$C$43+E1213*'Stock Statistics'!$C$44+F1213*'Stock Statistics'!$C$45+G1213*'Stock Statistics'!$C$46+H1213*'Stock Statistics'!$C$47+I1213*'Stock Statistics'!$C$48+J1213*'Stock Statistics'!$C$49+K1213*'Stock Statistics'!$C$50,"") -> 0.0099971899 | M1213: 220.5601 | N1213: 270.6683 | O1213: =M1213/M1214-1 -> -0.0072198884 | Q1213: =B1213*'Portfolio 2 & 3'!$F$7+C1213*'Portfolio 2 & 3'!$F$8+D1213*'Portfolio 2 & 3'!$F$9+E1213*'Portfolio 2 & 3'!$F$10+F1213*'Portfolio 2 & 3'!$F$11+G1213*'Portfolio 2 & 3'!$F$12+H1213*'Portfolio 2 & 3'!$F$13+I1213*'Portfolio 2 & 3'!$F$14+J1213*'Portfolio 2 & 3'!$F$15+K1213*'Portfolio 2 & 3'!$F$16 -> 0.0094669859 | R1213: =B1213*'Portfolio 2 & 3'!$B$23+C1213*'Portfolio 2 & 3'!$B$24+D1213*'Portfolio 2 & 3'!$B$25+E1213*'Portfolio 2 & 3'!$B$26+F1213*'Portfolio 2 & 3'!$B$27+G1213*'Portfolio 2 & 3'!$B$28+H1213*'Portfolio 2 & 3'!$B$29+I1213*'Portfolio 2 & 3'!$B$30+J1213*'Portfolio 2 & 3'!$B$31+K1213*'Portfolio 2 & 3'!$B$32 -> 0.012996334 | S1213: =IFERROR(AVERAGE(O1213,P1213),"") -> -0.0072198884
A1214: 44301 | B1214: -0.0027 | C1214: 0.020688523 | D1214: 0.0043613707 | E1214: -0.01425 | F1214: 0.030105113 | G1214: -0.008911597 | H1214: -0.0018651193 | I1214: 0.02759585 | J1214: 0.0042471042 | K1214: 0.0072760521 | L1214: =IFERROR(B1214*'Stock Statistics'!$C$41+C1214*'Stock Statistics'!$C$42+D1214*'Stock Statistics'!$C$43+E1214*'Stock Statistics'!$C$44+F1214*'Stock Statistics'!$C$45+G1214*'Stock Statistics'!$C$46+H1214*'Stock Statistics'!$C$47+I1214*'Stock Statistics'!$C$48+J1214*'Stock Statistics'!$C$49+K1214*'Stock Statistics'!$C$50,"") -> 0.0066547296 | M1214: 222.1641 | O1214: =M1214/M1215-1 -> -0.0081029918 | Q1214: =B1214*'Portfolio 2 & 3'!$F$7+C1214*'Portfolio 2 & 3'!$F$8+D1214*'Portfolio 2 & 3'!$F$9+E1214*'Portfolio 2 & 3'!$F$10+F1214*'Portfolio 2 & 3'!$F$11+G1214*'Portfolio 2 & 3'!$F$12+H1214*'Portfolio 2 & 3'!$F$13+I1214*'Portfolio 2 & 3'!$F$14+J1214*'Portfolio 2 & 3'!$F$15+K1214*'Portfolio 2 & 3'!$F$16 -> 0.007214254 | R1214: =B1214*'Portfolio 2 & 3'!$B$23+C1214*'Portfolio 2 & 3'!$B$24+D1214*'Portfolio 2 & 3'!$B$25+E1214*'Portfolio 2 & 3'!$B$26+F1214*'Portfolio 2 & 3'!$B$27+G1214*'Portfolio 2 & 3'!$B$28+H1214*'Portfolio 2 & 3'!$B$29+I1214*'Portfolio 2 & 3'!$B$30+J1214*'Portfolio 2 & 3'!$B$31+K1214*'Portfolio 2 & 3'!$B$32 -> 0.015057383 | S1214: =IFERROR(AVERAGE(O1214,P1214),"") -> -0.0081029918
A1215: 44299 | B1215: -0.006 | C1215: -0.0030737332 | D1215: -0.0098704503 | E1215: -0.00136 | F1215: -0.019511707 | G1215: 0.0053156543 | H1215: 0 | I1215: 7.3594348e-05 | J1215: -0.0040650407 | K1215: -0.0067409407 | L1215: =IFERROR(B1215*'Stock Statistics'!$C$41+C1215*'Stock Statistics'!$C$42+D1215*'Stock Statistics'!$C$43+E1215*'Stock Statistics'!$C$44+F1215*'Stock Statistics'!$C$45+G1215*'Stock Statistics'!$C$46+H1215*'Stock Statistics'!$C$47+I1215*'Stock Statistics'!$C$48+J1215*'Stock Statistics'!$C$49+K1215*'Stock Statistics'!$C$50,"") -> -0.0045232623 | M1215: 223.979 | O1215: =M1215/M1216-1 -> 0.021622105 | Q1215: =B1215*'Portfolio 2 & 3'!$F$7+C1215*'Portfolio 2 & 3'!$F$8+D1215*'Portfolio 2 & 3'!$F$9+E1215*'Portfolio 2 & 3'!$F$10+F1215*'Portfolio 2 & 3'!$F$11+G1215*'Portfolio 2 & 3'!$F$12+H1215*'Portfolio 2 & 3'!$F$13+I1215*'Portfolio 2 & 3'!$F$14+J1215*'Portfolio 2 & 3'!$F$15+K1215*'Portfolio 2 & 3'!$F$16 -> -0.0049495191 | R1215: =B1215*'Portfolio 2 & 3'!$B$23+C1215*'Portfolio 2 & 3'!$B$24+D1215*'Portfolio 2 & 3'!$B$25+E1215*'Portfolio 2 & 3'!$B$26+F1215*'Portfolio 2 & 3'!$B$27+G1215*'Portfolio 2 & 3'!$B$28+H1215*'Portfolio 2 & 3'!$B$29+I1215*'Portfolio 2 & 3'!$B$30+J1215*'Portfolio 2 & 3'!$B$31+K1215*'Portfolio 2 & 3'!$B$32 -> -0.0047197531 | S1215: =IFERROR(AVERAGE(O1215,P1215),"") -> 0.021622105
A1216: 44298 | B1216: -0.0121 | C1216: -0.014941952 | D1216: 0.0014415157 | E1216: -0.01154 | F1216: -0.028671397 | G1216: -0.0080965264 | H1216: -0.025606508 | I1216: -0.0058530875 | J1216: -0.0024112231 | K1216: 0.032925073 | L1216: =IFERROR(B1216*'Stock Statistics'!$C$41+C1216*'Stock Statistics'!$C$42+D1216*'Stock Statistics'!$C$43+E1216*'Stock Statistics'!$C$44+F1216*'Stock Statistics'!$C$45+G1216*'Stock Statistics'!$C$46+H1216*'Stock Statistics'!$C$47+I1216*'Stock Statistics'!$C$48+J1216*'Stock Statistics'!$C$49+K1216*'Stock Statistics'!$C$50,"") -> -0.0074854105 | M1216: 219.2386 | O1216: =M1216/M1217-1 -> 0.0031200142 | Q1216: =B1216*'Portfolio 2 & 3'!$F$7+C1216*'Portfolio 2 & 3'!$F$8+D1216*'Portfolio 2 & 3'!$F$9+E1216*'Portfolio 2 & 3'!$F$10+F1216*'Portfolio 2 & 3'!$F$11+G1216*'Portfolio 2 & 3'!$F$12+H1216*'Portfolio 2 & 3'!$F$13+I1216*'Portfolio 2 & 3'!$F$14+J1216*'Portfolio 2 & 3'!$F$15+K1216*'Portfolio 2 & 3'!$F$16 -> -0.0087417134 | R1216: =B1216*'Portfolio 2 & 3'!$B$23+C1216*'Portfolio 2 & 3'!$B$24+D1216*'Portfolio 2 & 3'!$B$25+E1216*'Portfolio 2 & 3'!$B$26+F1216*'Portfolio 2 & 3'!$B$27+G1216*'Portfolio 2 & 3'!$B$28+H1216*'Portfolio 2 & 3'!$B$29+I1216*'Portfolio 2 & 3'!$B$30+J1216*'Portfolio 2 & 3'!$B$31+K1216*'Portfolio 2 & 3'!$B$32 -> -0.0093218694 | S1216: =IFERROR(AVERAGE(O1216,P1216),"") -> 0.0031200142
A1217: 44295 | B1217: 0.0181 | C1217: 0.014670327 | D1217: -0.022298284 | E1217: 0.02892 | F1217: 0.092946675 | G1217: -0.017367175 | H1217: 0.0083579774 | I1217: 0.059288538 | J1217: 0.0077313894 | K1217: 0.0012170117 | L1217: =IFERROR(B1217*'Stock Statistics'!$C$41+C1217*'Stock Statistics'!$C$42+D1217*'Stock Statistics'!$C$43+E1217*'Stock Statistics'!$C$44+F1217*'Stock Statistics'!$C$45+G1217*'Stock Statistics'!$C$46+H1217*'Stock Statistics'!$C$47+I1217*'Stock Statistics'!$C$48+J1217*'Stock Statistics'!$C$49+K1217*'Stock Statistics'!$C$50,"") -> 0.019156646 | M1217: 218.5567 | O1217: =M1217/M1218-1 -> 0.007487586 | Q1217: =B1217*'Portfolio 2 & 3'!$F$7+C1217*'Portfolio 2 & 3'!$F$8+D1217*'Portfolio 2 & 3'!$F$9+E1217*'Portfolio 2 & 3'!$F$10+F1217*'Portfolio 2 & 3'!$F$11+G1217*'Portfolio 2 & 3'!$F$12+H1217*'Portfolio 2 & 3'!$F$13+I1217*'Portfolio 2 & 3'!$F$14+J1217*'Portfolio 2 & 3'!$F$15+K1217*'Portfolio 2 & 3'!$F$16 -> 0.018007099 | R1217: =B1217*'Portfolio 2 & 3'!$B$23+C1217*'Portfolio 2 & 3'!$B$24+D1217*'Portfolio 2 & 3'!$B$25+E1217*'Portfolio 2 & 3'!$B$26+F1217*'Portfolio 2 & 3'!$B$27+G1217*'Portfolio 2 & 3'!$B$28+H1217*'Portfolio 2 & 3'!$B$29+I1217*'Portfolio 2 & 3'!$B$30+J1217*'Portfolio 2 & 3'!$B$31+K1217*'Portfolio 2 & 3'!$B$32 -> 0.033195322 | S1217: =IFERROR(AVERAGE(O1217,P1217),"") -> 0.007487586
A1218: 44294 | B1218: -0.0229 | C1218: -0.00047242664 | D1218: 0.00015102698 | E1218: -0.03568 | F1218: 0.019493177 | G1218: -0.010806764 | H1218: 0.037972263 | I1218: -0.021313714 | J1218: -0.032278752 | K1218: 0.0065241995 | L1218: =IFERROR(B1218*'Stock Statistics'!$C$41+C1218*'Stock Statistics'!$C$42+D1218*'Stock Statistics'!$C$43+E1218*'Stock Statistics'!$C$44+F1218*'Stock Statistics'!$C$45+G1218*'Stock Statistics'!$C$46+H1218*'Stock Statistics'!$C$47+I1218*'Stock Statistics'!$C$48+J1218*'Stock Statistics'!$C$49+K1218*'Stock Statistics'!$C$50,"") -> -0.0059310989 | M1218: 216.9324 | O1218: =M1218/M1219-1 -> 0.010954331 | Q1218: =B1218*'Portfolio 2 & 3'!$F$7+C1218*'Portfolio 2 & 3'!$F$8+D1218*'Portfolio 2 & 3'!$F$9+E1218*'Portfolio 2 & 3'!$F$10+F1218*'Portfolio 2 & 3'!$F$11+G1218*'Portfolio 2 & 3'!$F$12+H1218*'Portfolio 2 & 3'!$F$13+I1218*'Portfolio 2 & 3'!$F$14+J1218*'Portfolio 2 & 3'!$F$15+K1218*'Portfolio 2 & 3'!$F$16 -> -0.0025041784 | R1218: =B1218*'Portfolio 2 & 3'!$B$23+C1218*'Portfolio 2 & 3'!$B$24+D1218*'Portfolio 2 & 3'!$B$25+E1218*'Portfolio 2 & 3'!$B$26+F1218*'Portfolio 2 & 3'!$B$27+G1218*'Portfolio 2 & 3'!$B$28+H1218*'Portfolio 2 & 3'!$B$29+I1218*'Portfolio 2 & 3'!$B$30+J1218*'Portfolio 2 & 3'!$B$31+K1218*'Portfolio 2 & 3'!$B$32 -> -0.0059168822 | S1218: =IFERROR(AVERAGE(O1218,P1218),"") -> 0.010954331
A1219: 44293 | B1219: 0.0065 | C1219: 0.0022581996 | D1219: 0.0059758939 | E1219: 0.01283 | F1219: 0.011391019 | G1219: 0.0033317926 | H1219: 0.015296582 | I1219: 0.0072580029 | J1219: -0.0092656324 | K1219: -0.0064687674 | L1219: =IFERROR(B1219*'Stock Statistics'!$C$41+C1219*'Stock Statistics'!$C$42+D1219*'Stock Statistics'!$C$43+E1219*'Stock Statistics'!$C$44+F1219*'Stock Statistics'!$C$45+G1219*'Stock Statistics'!$C$46+H1219*'Stock Statistics'!$C$47+I1219*'Stock Statistics'!$C$48+J1219*'Stock Statistics'!$C$49+K1219*'Stock Statistics'!$C$50,"") -> 0.004910709 | M1219: 214.5818 | O1219: =M1219/M1220-1 -> -0.0036338411 | Q1219: =B1219*'Portfolio 2 & 3'!$F$7+C1219*'Portfolio 2 & 3'!$F$8+D1219*'Portfolio 2 & 3'!$F$9+E1219*'Portfolio 2 & 3'!$F$10+F1219*'Portfolio 2 & 3'!$F$11+G1219*'Portfolio 2 & 3'!$F$12+H1219*'Portfolio 2 & 3'!$F$13+I1219*'Portfolio 2 & 3'!$F$14+J1219*'Portfolio 2 & 3'!$F$15+K1219*'Portfolio 2 & 3'!$F$16 -> 0.0049990601 | R1219: =B1219*'Portfolio 2 & 3'!$B$23+C1219*'Portfolio 2 & 3'!$B$24+D1219*'Portfolio 2 & 3'!$B$25+E1219*'Portfolio 2 & 3'!$B$26+F1219*'Portfolio 2 & 3'!$B$27+G1219*'Portfolio 2 & 3'!$B$28+H1219*'Portfolio 2 & 3'!$B$29+I1219*'Portfolio 2 & 3'!$B$30+J1219*'Portfolio 2 & 3'!$B$31+K1219*'Portfolio 2 & 3'!$B$32 -> 0.0049386606 | S1219: =IFERROR(AVERAGE(O1219,P1219),"") -> -0.0036338411
A1220: 44292 | B1220: 0.0037 | C1220: -0.030628818 | D1220: 0.022155503 | E1220: 0.0188 | F1220: 0.037617911 | G1220: -0.0088948273 | H1220: 0.015296582 | I1220: 0.015438324 | J1220: -0.0052143685 | K1220: -0.0071970791 | L1220: =IFERROR(B1220*'Stock Statistics'!$C$41+C1220*'Stock Statistics'!$C$42+D1220*'Stock Statistics'!$C$43+E1220*'Stock Statistics'!$C$44+F1220*'Stock Statistics'!$C$45+G1220*'Stock Statistics'!$C$46+H1220*'Stock Statistics'!$C$47+I1220*'Stock Statistics'!$C$48+J1220*'Stock Statistics'!$C$49+K1220*'Stock Statistics'!$C$50,"") -> 0.0061073228 | M1220: 215.3644 | Q1220: =B1220*'Portfolio 2 & 3'!$F$7+C1220*'Portfolio 2 & 3'!$F$8+D1220*'Portfolio 2 & 3'!$F$9+E1220*'Portfolio 2 & 3'!$F$10+F1220*'Portfolio 2 & 3'!$F$11+G1220*'Portfolio 2 & 3'!$F$12+H1220*'Portfolio 2 & 3'!$F$13+I1220*'Portfolio 2 & 3'!$F$14+J1220*'Portfolio 2 & 3'!$F$15+K1220*'Portfolio 2 & 3'!$F$16 -> 0.0074760509 | R1220: =B1220*'Portfolio 2 & 3'!$B$23+C1220*'Portfolio 2 & 3'!$B$24+D1220*'Portfolio 2 & 3'!$B$25+E1220*'Portfolio 2 & 3'!$B$26+F1220*'Portfolio 2 & 3'!$B$27+G1220*'Portfolio 2 & 3'!$B$28+H1220*'Portfolio 2 & 3'!$B$29+I1220*'Portfolio 2 & 3'!$B$30+J1220*'Portfolio 2 & 3'!$B$31+K1220*'Portfolio 2 & 3'!$B$32 -> 0.003429969
A1221: 44291 | B1221: 0.012 | C1221: 0.046500028 | D1221: 0.013536201 | E1221: 0.00176 | F1221: -0.0041874151 | G1221: 0.021247563 | H1221: 0.0098440837 | I1221: 0.0017096674 | J1221: 0.003170242 | K1221: -0.0038593875 | L1221: =IFERROR(B1221*'Stock Statistics'!$C$41+C1221*'Stock Statistics'!$C$42+D1221*'Stock Statistics'!$C$43+E1221*'Stock Statistics'!$C$44+F1221*'Stock Statistics'!$C$45+G1221*'Stock Statistics'!$C$46+H1221*'Stock Statistics'!$C$47+I1221*'Stock Statistics'!$C$48+J1221*'Stock Statistics'!$C$49+K1221*'Stock Statistics'!$C$50,"") -> 0.010172098 | M1221: 215.3644 | Q1221: =B1221*'Portfolio 2 & 3'!$F$7+C1221*'Portfolio 2 & 3'!$F$8+D1221*'Portfolio 2 & 3'!$F$9+E1221*'Portfolio 2 & 3'!$F$10+F1221*'Portfolio 2 & 3'!$F$11+G1221*'Portfolio 2 & 3'!$F$12+H1221*'Portfolio 2 & 3'!$F$13+I1221*'Portfolio 2 & 3'!$F$14+J1221*'Portfolio 2 & 3'!$F$15+K1221*'Portfolio 2 & 3'!$F$16 -> 0.0098824137 | R1221: =B1221*'Portfolio 2 & 3'!$B$23+C1221*'Portfolio 2 & 3'!$B$24+D1221*'Portfolio 2 & 3'!$B$25+E1221*'Portfolio 2 & 3'!$B$26+F1221*'Portfolio 2 & 3'!$B$27+G1221*'Portfolio 2 & 3'!$B$28+H1221*'Portfolio 2 & 3'!$B$29+I1221*'Portfolio 2 & 3'!$B$30+J1221*'Portfolio 2 & 3'!$B$31+K1221*'Portfolio 2 & 3'!$B$32 -> 0.012755909
A1222: 44287 | B1222: - | C1222: -0.0075539502 | D1222: 0.041245561 | E1222: 0.02921 | F1222: - | G1222: -0.00064286132 | H1222: 0.014286312 | I1222: 0.0064919828 | J1222: 0.0087948404 | K1222: 0.010162817 | M1222: 215.3644

Sheet Stock Statistics
A1: Statistic | B1: ABBOTINDIA | C1: ALKEM | D1: AUROPHARMA | E1: LUPIN | F1: ZYDUSLIFE | G1: TORNTPHARM | H1: DRREDDY | I1: SUNPHARMA | J1: CIPLA | K1: DIVISLAB | L1: Portfolio | N1: Beta according to SBI
A2: Average daily return | B2: =AVERAGE(Return!B2:B1222) -> 0.00057563577 | C2: =AVERAGE(Return!C2:C1222) -> 0.00070174899 | D2: =AVERAGE(Return!D2:D1222) -> 0.00041206038 | E2: =AVERAGE(Return!E2:E1222) -> -0.00083860656 | F2: =AVERAGE(Return!F2:F1222) -> 0.00073313558 | G2: =AVERAGE(Return!G2:G1222) -> 0.00069980424 | H2: =AVERAGE(Return!H2:H1222) -> 0.00034703912 | I2: =AVERAGE(Return!I2:I1222) -> 0.00090240985 | ... L2: =AVERAGE(Return!L2:L1222) -> 0.00044181682 | N2: ABBOTINDIA | O2: ALKEM | P2: AUROPHARMA | Q2: LUPIN | R2: ZYDUSLIFE | S2: TORNTPHARM | T2: DRREDDY | U2: SUNPHARMA | V2: CIPLA | W2: DIVISLAB | X2: Portfolio
A3: Annualised Return | B3: =(1+B2)^250-1 -> 0.15473114 | C3: =(1+C2)^250-1 -> 0.19169388 | D3: =(1+D2)^250-1 -> 0.10848462 | E3: =(1+E2)^250-1 -> -0.18920465 | F3: =(1+F2)^250-1 -> 0.2010747 | G3: =(1+G2)^250-1 -> 0.19111504 | H3: =(1+H2)^250-1 -> 0.090618241 | I3: =(1+I2)^250-1 -> 0.25294995 | ... L3: =(1+L2)^250-1 -> 0.11675796 | N3: =SLOPE(Return!B2:B1211,Return!$O2:$O1211) -> 0.045935988 | O3: =SLOPE(Return!C2:C1211,Return!$O2:$O1211) -> 0.22438762 | P3: =SLOPE(Return!D2:D1211,Return!$O2:$O1211) -> 0.2777692 | Q3: =SLOPE(Return!E2:E1211,Return!$O2:$O1211) -> 0.25092372 | R3: =SLOPE(Return!F2:F1211,Return!$O2:$O1211) -> 0.11041863 | S3: =SLOPE(Return!G2:G1211,Return!$O2:$O1211) -> 0.10610691 | T3: =SLOPE(Return!H2:H1211,Return!$O2:$O1211) -> 0.2112045 | U3: =SLOPE(Return!I2:I1211,Return!$O2:$O1211) -> 0.18545173 | ... X3: =SLOPE(Return!L2:L1211,Return!$O2:$O1211) -> 0.19945766
A4: Std Dev | B4: =_xlfn.STDEV.S(Return!B2:B1222) -> 0.014732172 | C4: =_xlfn.STDEV.S(Return!C2:C1222) -> 0.014563005 | D4: =_xlfn.STDEV.S(Return!D2:D1222) -> 0.018773751 | E4: =_xlfn.STDEV.S(Return!E2:E1222) -> 0.016286497 | F4: =_xlfn.STDEV.S(Return!F2:F1222) -> 0.016137311 | G4: =_xlfn.STDEV.S(Return!G2:G1222) -> 0.020651316 | H4: =_xlfn.STDEV.S(Return!H2:H1222) -> 0.013477545 | I4: =_xlfn.STDEV.S(Return!I2:I1222) -> 0.012903922 | ... L4: =_xlfn.STDEV.S(Return!L2:L1222) -> 0.0064362724
A5: Annualised Std Dev | B5: =B4*SQRT(250) -> 0.2329361 | C5: =C4*SQRT(250) -> 0.23026133 | D5: =D4*SQRT(250) -> 0.29683907 | E5: =E4*SQRT(250) -> 0.25751213 | F5: =F4*SQRT(250) -> 0.25515329 | G5: =G4*SQRT(250) -> 0.32652598 | H5: =H4*SQRT(250) -> 0.21309869 | I5: =I4*SQRT(250) -> 0.20402893 | ... L5: =L4*SQRT(250) -> 0.1017664 | N5: Beta according to Nippon
N6: ABBOTINDIA | O6: ALKEM | P6: AUROPHARMA | Q6: LUPIN | R6: ZYDUSLIFE | S6: TORNTPHARM | T6: DRREDDY | U6: SUNPHARMA | V6: CIPLA | W6: DIVISLAB | X6: Portfolio
N7: =SLOPE(Return!B2:B1211,Return!$P2:$P1211) -> -0.026022458 | O7: =SLOPE(Return!C2:C1211,Return!$P2:$P1211) -> 0.014063207 | P7: =SLOPE(Return!D2:D1211,Return!$P2:$P1211) -> -0.030827369 | Q7: =SLOPE(Return!E2:E1211,Return!$P2:$P1211) -> -0.033248149 | R7: =SLOPE(Return!F2:F1211,Return!$P2:$P1211) -> 0.024797469 | S7: =SLOPE(Return!G2:G1211,Return!$P2:$P1211) -> 0.17293478 | T7: =SLOPE(Return!H2:H1211,Return!$P2:$P1211) -> 0.025535619 | U7: =SLOPE(Return!I2:I1211,Return!$P2:$P1211) -> 0.050417095 | ... X7: =SLOPE(Return!L2:L1211,Return!$P2:$P1211) -> 0.01641682
B8: Covariance
C10: ALKEM | D10: AUROPHARMA | E10: LUPIN | F10: ZYDUSLIFE | G10: TORNTPHARM | H10: DRREDDY | I10: SUNPHARMA | J10: CIPLA | K10: DIVISLAB | V10: *Dr Reddy stock was split in 1:5
B11: ABBOTINDIA | C11: =_xlfn.COVARIANCE.S(Return!$B$2:$B$1222,Return!C$2:C$1222) -> 4.031475e-06 | D11: =_xlfn.COVARIANCE.S(Return!$B$2:$B$1222,Return!D$2:D$1222) -> -9.7300499e-07 | E11: =_xlfn.COVARIANCE.S(Return!$B$2:$B$1222,Return!E$2:E$1222) -> 2.9718721e-06 | F11: =_xlfn.COVARIANCE.S(Return!$B$2:$B$1222,Return!F$2:F$1222) -> 6.2970134e-05 | G11: =_xlfn.COVARIANCE.S(Return!$B$2:$B$1222,Return!G$2:G$1222) -> -4.731463e-06 | H11: =_xlfn.COVARIANCE.S(Return!$B$2:$B$1222,Return!H$2:H$1222) -> 7.1374483e-06 | I11: =_xlfn.COVARIANCE.S(Return!$B$2:$B$1222,Return!I$2:I$1222) -> 1.6086347e-06 | J11: =_xlfn.COVARIANCE.S(Return!$B$2:$B$1222,Return!J$2:J$1222) -> -9.7495095e-06 | K11: =_xlfn.COVARIANCE.S(Return!$B$2:$B$1222,Return!K$2:K$1222) -> 8.1942435e-06 | P11: ABBOTINDIA | Q11: ALKEM | R11: AUROPHARMA | S11: LUPIN | T11: ZYDUSLIFE | U11: TORNTPHARM | V11: DRREDDY | W11: SUNPHARMA | X11: CIPLA | Y11: DIVISLAB | Z11: SBI MF | AA11: Nippon MF
B12: ALKEM | D12: =_xlfn.COVARIANCE.S(Return!$C$2:$C$1222,Return!D$2:D$1222) -> 2.0172359e-05 | E12: =_xlfn.COVARIANCE.S(Return!$C$2:$C$1222,Return!E$2:E$1222) -> -4.5822191e-08 | F12: =_xlfn.COVARIANCE.S(Return!$C$2:$C$1222,Return!F$2:F$1222) -> 2.1280782e-05 | G12: =_xlfn.COVARIANCE.S(Return!$C$2:$C$1222,Return!G$2:G$1222) -> 1.2751614e-05 | H12: =_xlfn.COVARIANCE.S(Return!$C$2:$C$1222,Return!H$2:H$1222) -> 9.4844112e-06 | I12: =_xlfn.COVARIANCE.S(Return!$C$2:$C$1222,Return!I$2:I$1222) -> 1.9998704e-05 | J12: =_xlfn.COVARIANCE.S(Return!$C$2:$C$1222,Return!J$2:J$1222) -> 1.4373805e-05 | K12: =_xlfn.COVARIANCE.S(Return!$C$2:$C$1222,Return!K$2:K$1222) -> 2.6776763e-05 | N12: Start date | O12: =Return!A1211 -> 44305 | P12: 14724.8 | Q12: 2745.55 | R12: 987.3 | S12: 1064.65 | T12: 456.5 | U12: 2596.2 | V12: 4968.11 | W12: 654.45 | X12: 944.35 | Y12: 3779.7 | Z12: =Return!M1211 -> 222.3549 | AA12: =Return!N1211 -> 273.1368
B13: AUROPHARMA | E13: =_xlfn.COVARIANCE.S(Return!$D$2:$D$1222,Return!E$2:E$1222) -> 5.1450215e-05 | F13: =_xlfn.COVARIANCE.S(Return!$D$2:$D$1222,Return!F$2:F$1222) -> 1.1415962e-05 | G13: =_xlfn.COVARIANCE.S(Return!$D$2:$D$1222,Return!G$2:G$1222) -> 3.7897018e-05 | H13: =_xlfn.COVARIANCE.S(Return!$D$2:$D$1222,Return!H$2:H$1222) -> 4.7726193e-05 | I13: =_xlfn.COVARIANCE.S(Return!$D$2:$D$1222,Return!I$2:I$1222) -> 1.4668746e-05 | J13: =_xlfn.COVARIANCE.S(Return!$D$2:$D$1222,Return!J$2:J$1222) -> 1.2523297e-05 | K13: =_xlfn.COVARIANCE.S(Return!$D$2:$D$1222,Return!K$2:K$1222) -> 3.2801129e-05 | N13: End Date | O13: =Return!A2 -> 46080 | P13: 26530 | Q13: 5639.5 | R13: 1220.4 | S13: 2301.9 | T13: 921.7 | U13: 4333.3 | V13: 6431.5 | W13: 1737 | X13: 1348.2 | Y13: 6408.5 | Z13: =Return!M2 -> 497.1341 | AA13: =Return!N2 -> 576.9248
B14: LUPIN | F14: =_xlfn.COVARIANCE.S(Return!$E$2:$E$1222,Return!F$2:F$1222) -> 1.4631847e-05 | G14: =_xlfn.COVARIANCE.S(Return!$E$2:$E$1222,Return!G2:G1222) -> 5.5595583e-05 | H14: =_xlfn.COVARIANCE.S(Return!$E$2:$E$1222,Return!H2:H1222) -> 6.8511272e-05 | I14: =_xlfn.COVARIANCE.S(Return!$E$2:$E$1222,Return!I2:I1222) -> 5.6225766e-06 | J14: =_xlfn.COVARIANCE.S(Return!$E$2:$E$1222,Return!J2:J1222) -> 7.112167e-06 | K14: =_xlfn.COVARIANCE.S(Return!$E$2:$E$1222,Return!K2:K1222) -> 1.2826064e-05 | N14: Time | O14: =YEARFRAC(O12,O13,1) -> 4.8607942
B15: ZYDUSLIFE | G15: =_xlfn.COVARIANCE.S(Return!$F$2:$F$1222,Return!G$2:G$1222) -> 1.1332858e-05 | H15: =_xlfn.COVARIANCE.S(Return!$F$2:$F$1222,Return!H$2:H$1222) -> 8.2637962e-06 | I15: =_xlfn.COVARIANCE.S(Return!$F$2:$F$1222,Return!I$2:I$1222) -> 9.0745388e-06 | J15: =_xlfn.COVARIANCE.S(Return!$F$2:$F$1222,Return!J$2:J$1222) -> -6.9361765e-07 | K15: =_xlfn.COVARIANCE.S(Return!$F$2:$F$1222,Return!K$2:K$1222) -> 2.7814913e-08 | N15: Actual Return | P15: =(P13/P12)^(1/$O$14)-1 -> 0.1287612 | Q15: =(Q13/Q12)^(1/$O$14)-1 -> 0.15961224 | R15: =(R13/R12)^(1/$O$14)-1 -> 0.04457076 | S15: =(S13/S12)^(1/$O$14)-1 -> 0.17190932 | T15: =(T13/T12)^(1/$O$14)-1 -> 0.15552025 | U15: =(U13/U12)^(1/$O$14)-1 -> 0.1111442 | V15: =(V13/V12)^(1/$O$14)-1 -> 0.05454814 | W15: =(W13/W12)^(1/$O$14)-1 -> 0.22239841 | ... Y15: =(Y13/Y12)^(1/$O$14)-1 -> 0.11473893
B16: TORNTPHARM | H16: =_xlfn.COVARIANCE.S(Return!$G$2:$G$1222,Return!H$2:H$1222) -> 3.0445859e-05 | I16: =_xlfn.COVARIANCE.S(Return!$G$2:$G$1222,Return!I$2:I$1222) -> 1.4711128e-05 | J16: =_xlfn.COVARIANCE.S(Return!$G$2:$G$1222,Return!J$2:J$1222) -> 8.1431e-06 | K16: =_xlfn.COVARIANCE.S(Return!$G$2:$G$1222,Return!K$2:K$1222) -> -5.445339e-06 | N16: Expected Return | O16: SBI | P16: =$P$18+N3*(P19-$P$18) -> 0.073336239 | Q16: =$P$18+O3*(Q19-$P$18) -> 0.093289447 | R16: =$P$18+P3*(R19-$P$18) -> 0.0992582 | S16: =$P$18+Q3*(S19-$P$18) -> 0.096256527 | T16: =$P$18+R3*(T19-$P$18) -> 0.080546235 | U16: =$P$18+S3*(U19-$P$18) -> 0.080064129 | V16: =$P$18+T3*(V19-$P$18) -> 0.091815403 | W16: =$P$18+U3*(W19-$P$18) -> 0.088935909 | ... Y16: =$P$18+W3*(Y19-$P$18) -> 0.10910196
B17: DRREDDY | I17: =_xlfn.COVARIANCE.S(Return!$H$2:$H$1222,Return!I$2:I$1222) -> 1.8442668e-06 | J17: =_xlfn.COVARIANCE.S(Return!$H$2:$H$1222,Return!J$2:J$1222) -> 1.1254041e-05 | K17: =_xlfn.COVARIANCE.S(Return!$H$2:$H$1222,Return!K$2:K$1222) -> 1.3179578e-05 | O17: Nippon | P17: =$P$18+N7*(P20-$P$18) -> 0.065647369 | Q17: =$P$18+O7*(Q20-$P$18) -> 0.069579507 | R17: =$P$18+P7*(R20-$P$18) -> 0.06517604 | S17: =$P$18+Q7*(S20-$P$18) -> 0.064938577 | T17: =$P$18+R7*(T20-$P$18) -> 0.070632467 | U17: =$P$18+S7*(U20-$P$18) -> 0.085163754 | V17: =$P$18+T7*(V20-$P$18) -> 0.070704875 | W17: =$P$18+U7*(W20-$P$18) -> 0.073145583 | ... Y17: =$P$18+W7*(Y20-$P$18) -> 0.061485914
B18: SUNPHARMA | J18: =_xlfn.COVARIANCE.S(Return!$I$2:$I$1222,Return!J$2:J$1222) -> 2.4152633e-05 | K18: =_xlfn.COVARIANCE.S(Return!$I$2:$I$1222,Return!K$2:K$1222) -> 2.7605554e-05 | N18: Rf | P18: 0.0682 | Q18: 0.0682 | R18: 0.0682 | S18: 0.0682 | T18: 0.0682 | U18: 0.0682 | V18: 0.0682 | W18: 0.0682 | X18: 0.0682 | Y18: 0.0682
B19: CIPLA | K19: =_xlfn.COVARIANCE.S(Return!$J$2:$J$1222,Return!K$2:K$1222) -> 6.3869456e-05 | N19: Rm | O19: SBI | P19: =RATE($O$14,0,-$Z$12,$Z$13,0) -> 0.18001297 | Q19: =RATE($O$14,0,-$Z$12,$Z$13,0) -> 0.18001297 | R19: =RATE($O$14,0,-$Z$12,$Z$13,0) -> 0.18001297 | S19: =RATE($O$14,0,-$Z$12,$Z$13,0) -> 0.18001297 | T19: =RATE($O$14,0,-$Z$12,$Z$13,0) -> 0.18001297 | U19: =RATE($O$14,0,-$Z$12,$Z$13,0) -> 0.18001297 | V19: =RATE($O$14,0,-$Z$12,$Z$13,0) -> 0.18001297 | W19: =RATE($O$14,0,-$Z$12,$Z$13,0) -> 0.18001297 | ... Y19: =RATE($O$14,0,-$Z$12,$Z$13,0) -> 0.18001297
B20: DIVISLAB | O20: Nippon | P20: =RATE($O$14,0,-$AA$12,$AA$13,0) -> 0.16629337 | Q20: =RATE($O$14,0,-$AA$12,$AA$13,0) -> 0.16629337 | R20: =RATE($O$14,0,-$AA$12,$AA$13,0) -> 0.16629337 | S20: =RATE($O$14,0,-$AA$12,$AA$13,0) -> 0.16629337 | T20: =RATE($O$14,0,-$AA$12,$AA$13,0) -> 0.16629337 | U20: =RATE($O$14,0,-$AA$12,$AA$13,0) -> 0.16629337 | V20: =RATE($O$14,0,-$AA$12,$AA$13,0) -> 0.16629337 | W20: =RATE($O$14,0,-$AA$12,$AA$13,0) -> 0.16629337 | ... Y20: =RATE($O$14,0,-$AA$12,$AA$13,0) -> 0.16629337
N21: Jenson Alpha | P21: =(P15-P16)/100 -> 0.0005542496 | Q21: =(Q15-Q16)/100 -> 0.00066322796 | R21: =(R15-R16)/100 -> -0.0005468744 | S21: =(S15-S16)/100 -> 0.00075652794 | T21: =(T15-T16)/100 -> 0.00074974018 | U21: =(U15-U16)/100 -> 0.00031080073 | V21: =(V15-V16)/100 -> -0.00037267263 | W21: =(W15-W16)/100 -> 0.001334625 | ... Y21: =(Y15-Y16)/100 -> 5.6369729e-05
B23: Correlation | N23: Sharp Ratio of portfolio | O23: =(L3-P18)/L5 -> 0.47715121
N24: Treynor Ratio | O24: SBI | P24: Nippon
C25: ALKEM | D25: AUROPHARMA | E25: LUPIN | F25: ZYDUSLIFE | G25: TORNTPHARM | H25: DRREDDY | I25: SUNPHARMA | J25: CIPLA | K25: DIVISLAB | O25: =(L3-P18)/X3 -> 0.24344997 | P25: =(L3-Q18)/X7 -> 2.9578179
B26: ABBOTINDIA | C26: =CORREL(Return!$B$2:$B$1222,Return!C$2:C$1222) -> 0.018785609 | D26: =CORREL(Return!$B$2:$B$1222,Return!D$2:D$1222) -> -0.0035234172 | E26: =CORREL(Return!$B$2:$B$1222,Return!E$2:E$1222) -> 0.012398386 | F26: =CORREL(Return!$B$2:$B$1222,Return!F$2:F$1222) -> 0.26487237 | G26: =CORREL(Return!$B$2:$B$1222,Return!G$2:G$1222) -> -0.015545456 | H26: =CORREL(Return!$B$2:$B$1222,Return!H$2:H$1222) -> 0.03594359 | I26: =CORREL(Return!$B$2:$B$1222,Return!I$2:I$1222) -> 0.0084590994 | J26: =CORREL(Return!$B$2:$B$1222,Return!J$2:J$1222) -> -0.04587704 | K26: =CORREL(Return!$B$2:$B$1222,Return!K$2:K$1222) -> 0.032977363
B27: ALKEM | D27: =CORREL(Return!$C$2:$C$1222,Return!D$2:D$1222) -> 0.073782716 | E27: =CORREL(Return!$C$2:$C$1222,Return!E$2:E$1222) -> -0.00019319557 | F27: =CORREL(Return!$C$2:$C$1222,Return!F$2:F$1222) -> 0.09052833 | G27: =CORREL(Return!$C$2:$C$1222,Return!G$2:G$1222) -> 0.042400057 | H27: =CORREL(Return!$C$2:$C$1222,Return!H$2:H$1222) -> 0.048316099 | I27: =CORREL(Return!$C$2:$C$1222,Return!I$2:I$1222) -> 0.10642144 | J27: =CORREL(Return!$C$2:$C$1222,Return!J$2:J$1222) -> 0.068441255 | K27: =CORREL(Return!$C$2:$C$1222,Return!K$2:K$1222) -> 0.10904393
B28: AUROPHARMA | E28: =CORREL(Return!$D$2:$D$1222,Return!E$2:E$1222) -> 0.16827068 | F28: =CORREL(Return!$D$2:$D$1222,Return!F$2:F$1222) -> 0.037739588 | G28: =CORREL(Return!$D$2:$D$1222,Return!G$2:G$1222) -> 0.097747635 | H28: =CORREL(Return!$D$2:$D$1222,Return!H$2:H$1222) -> 0.1885985 | I28: =CORREL(Return!$D$2:$D$1222,Return!I$2:I$1222) -> 0.060550842 | J28: =CORREL(Return!$D$2:$D$1222,Return!J$2:J$1222) -> 0.046255655 | K28: =CORREL(Return!$D$2:$D$1222,Return!K$2:K$1222) -> 0.10361727
B29: LUPIN | F29: =CORREL(Return!$E$2:$E$1222,Return!F$2:F$1222) -> 0.055727533 | G29: =CORREL(Return!$E$2:$E$1222,Return!G$2:G$1222) -> 0.16529696 | H29: =CORREL(Return!$E$2:$E$1222,Return!H$2:H$1222) -> 0.31208064 | I29: =CORREL(Return!$E$2:$E$1222,Return!I$2:I$1222) -> 0.026753829 | J29: =CORREL(Return!$E$2:$E$1222,Return!J$2:J$1222) -> 0.030281088 | K29: =CORREL(Return!$E$2:$E$1222,Return!K$2:K$1222) -> 0.046704651
B30: ZYDUSLIFE | G30: =CORREL(Return!$F$2:$F$1222,Return!G$2:G$1222) -> 0.033992499 | H30: =CORREL(Return!$F$2:$F$1222,Return!H$2:H$1222) -> 0.037992135 | I30: =CORREL(Return!$F$2:$F$1222,Return!I$2:I$1222) -> 0.043563915 | J30: =CORREL(Return!$F$2:$F$1222,Return!J$2:J$1222) -> -0.0029796715 | K30: =CORREL(Return!$F$2:$F$1222,Return!K$2:K$1222) -> 0.00010219282
B31: TORNTPHARM | H31: =CORREL(Return!$G$2:$G$1222,Return!H$2:H$1222) -> 0.10937372 | I31: =CORREL(Return!$G$2:$G$1222,Return!I$2:I$1222) -> 0.055204756 | J31: =CORREL(Return!$G$2:$G$1222,Return!J$2:J$1222) -> 0.027342565 | K31: =CORREL(Return!$G$2:$G$1222,Return!K$2:K$1222) -> -0.015637654
B32: DRREDDY | I32: =CORREL(Return!$H$2:$H$1222,Return!I$2:I$1222) -> 0.01060314 | J32: =CORREL(Return!$H$2:$H$1222,Return!J$2:J$1222) -> 0.057894619 | K32: =CORREL(Return!$H$2:$H$1222,Return!K$2:K$1222) -> 0.057986702
B33: SUNPHARMA | J33: =CORREL(Return!$I$2:$I$1222,Return!J$2:J$1222) -> 0.12978962 | K33: =CORREL(Return!$I$2:$I$1222,Return!K$2:K$1222) -> 0.12687298
B34: CIPLA | K34: =CORREL(Return!$J$2:$J$1222,Return!K$2:K$1222) -> 0.26265449
B35: DIVISLAB
B39: A | C39: B
B40: Stock | C40: Weight
B41: ABBOTINDIA | C41: 0.1
B42: ALKEM | C42: 0.1
B43: AUROPHARMA | C43: 0.1
B44: LUPIN | C44: 0.1
B45: ZYDUSLIFE | C45: 0.1
B46: TORNTPHARM | C46: 0.1
B47: DRREDDY | C47: 0.1
B48: SUNPHARMA | C48: 0.1
B49: CIPLA | C49: 0.1
B50: DIVISLAB | C50: 0.1

Sheet Dashboard_Data
A1: Portfolio | B1: Return | C1: StdDev | D1: Beta | E1: Sharpe | F1: Treynor | G1: Alpha
A2: Portfolio 1 - Equal Weight | B2: ='Stock Statistics'!L3 -> 0.11675796 | C2: ='Stock Statistics'!L5 -> 0.1017664 | D2: ='Stock Statistics'!X3 -> 0.19945766 | E2: ='Stock Statistics'!O23 -> 0.47715121 | F2: ='Stock Statistics'!O25 -> 0.24344997 | G2: ='Stock Statistics'!L3-('Stock Statistics'!P18+'Stock Statistics'!X3*('Stock Statistics'!P19-'Stock Statistics'!P18)) -> 0.026256008
A3: Portfolio 2 - Fundamentals | B3: ='Portfolio 2 & 3'!J8 -> 0.11758308 | C3: ='Portfolio 2 & 3'!J10 -> 0.10414616 | D3: ='Portfolio 2 & 3'!J11 -> 0.20342873 | E3: ='Portfolio 2 & 3'!J15 -> 0.47417095 | F3: ='Portfolio 2 & 3'!J16 -> 0.24275372 | G3: ='Portfolio 2 & 3'!J14 -> 0.02663711
A4: Portfolio 3 - Markowitz | B4: ='Portfolio 2 & 3'!E24 -> 0.19368659 | C4: ='Portfolio 2 & 3'!E26 -> 0.11037186 | D4: ='Portfolio 2 & 3'!E27 -> 0.16794586 | E4: ='Portfolio 2 & 3'!E31 -> 1.1369437 | F4: ='Portfolio 2 & 3'!E32 -> 0.74718478 | G4: ='Portfolio 2 & 3'!E30 -> 0.10670806
A5: Portfolio 4 - SBI/Nippon Blend | B5: ='Portfolio 4-6'!B7 -> 0.19255796 | C5: ='Portfolio 4-6'!B9 -> 0.095140197 | D5: ='Portfolio 4-6'!B10 -> 0.52146352 | E5: ='Portfolio 4-6'!B14 -> 1.3071022 | F5: ='Portfolio 4-6'!B15 -> 0.23847874 | G5: ='Portfolio 4-6'!B13 -> 0.066051578
A6: Portfolio 5 - SBI Healthcare Fund | B6: ='Portfolio 4-6'!E7 -> 0.19929967 | C6: ='Portfolio 4-6'!E9 -> 0.13059446 | D6: ='Portfolio 4-6'!E10 -> 0.99917831 | E6: ='Portfolio 4-6'!E14 -> 1.0038685 | F6: ='Portfolio 4-6'!E15 -> 0.13120748 | G6: ='Portfolio 4-6'!E13 -> 0.019378572
A7: Portfolio 6 - Nippon Pharma Fund | B7: ='Portfolio 4-6'!H7 -> 0.18105334 | C7: ='Portfolio 4-6'!H9 -> 0.13267664 | D7: ='Portfolio 4-6'!H10 -> 0.034792532 | E7: ='Portfolio 4-6'!H14 -> 0.85058942 | F7: ='Portfolio 4-6'!H15 -> 3.2436083 | G7: ='Portfolio 4-6'!H13 -> 0.10896309

Sheet Return Long
A1: Date | B1: Portfolio | C1: Daily Return
A2: =Return!A2 -> 46080 | B2: Portfolio 1 - Equal Weight | C2: =Return!L2 -> -0.012797188
A3: =Return!A3 -> 46079 | B3: Portfolio 1 - Equal Weight | C3: =Return!L3 -> 0.010093915
A4: =Return!A4 -> 46078 | B4: Portfolio 1 - Equal Weight | C4: =Return!L4 -> 0.015955785
A5: =Return!A5 -> 46077 | B5: Portfolio 1 - Equal Weight | C5: =Return!L5 -> 0.0012648738
A6: =Return!A6 -> 46076 | B6: Portfolio 1 - Equal Weight | C6: =Return!L6 -> 0.0066240352
A7: =Return!A7 -> 46073 | B7: Portfolio 1 - Equal Weight | C7: =Return!L7 -> 0.00037415853
A8: =Return!A8 -> 46072 | B8: Portfolio 1 - Equal Weight | C8: =Return!L8 -> -0.0033390465
A9: =Return!A9 -> 46071 | B9: Portfolio 1 - Equal Weight | C9: =Return!L9 -> -0.0026785545
A10: =Return!A10 -> 46070 | B10: Portfolio 1 - Equal Weight | C10: =Return!L10 -> 0.0029539728
A11: =Return!A11 -> 46069 | B11: Portfolio 1 - Equal Weight | C11: =Return!L11 -> 0.011283731
A12: =Return!A12 -> 46066 | B12: Portfolio 1 - Equal Weight | C12: =Return!L12 -> -0.013715197
A13: =Return!A13 -> 46065 | B13: Portfolio 1 - Equal Weight | C13: =Return!L13 -> -0.0016248585
... A1211: =Return!A1211 -> 44305 | B1211: Portfolio 1 - Equal Weight | C1211: =Return!L1211 -> -0.0021794365
A1212: =Return!A2 -> 46080 | B1212: Portfolio 2 - Fundamentals | C1212: =Return!Q2 -> -0.013299705
A1213: =Return!A3 -> 46079 | B1213: Portfolio 2 - Fundamentals | C1213: =Return!Q3 -> 0.010822137
A1214: =Return!A4 -> 46078 | B1214: Portfolio 2 - Fundamentals | C1214: =Return!Q4 -> 0.016925966
A1215: =Return!A5 -> 46077 | B1215: Portfolio 2 - Fundamentals | C1215: =Return!Q5 -> 0.00064536416
A1216: =Return!A6 -> 46076 | B1216: Portfolio 2 - Fundamentals | C1216: =Return!Q6 -> 0.005933812
A1217: =Return!A7 -> 46073 | B1217: Portfolio 2 - Fundamentals | C1217: =Return!Q7 -> 0.00019418118
A1218: =Return!A8 -> 46072 | B1218: Portfolio 2 - Fundamentals | C1218: =Return!Q8 -> -0.0035525103
A1219: =Return!A9 -> 46071 | B1219: Portfolio 2 - Fundamentals | C1219: =Return!Q9 -> -0.0027990656
A1220: =Return!A10 -> 46070 | B1220: Portfolio 2 - Fundamentals | C1220: =Return!Q10 -> 0.0025484427
A1221: =Return!A11 -> 46069 | B1221: Portfolio 2 - Fundamentals | C1221: =Return!Q11 -> 0.011488836
A1222: =Return!A12 -> 46066 | B1222: Portfolio 2 - Fundamentals | C1222: =Return!Q12 -> -0.013585931
A1223: =Return!A13 -> 46065 | B1223: Portfolio 2 - Fundamentals | C1223: =Return!Q13 -> -0.00084215547
... A2421: =Return!A1211 -> 44305 | B2421: Portfolio 2 - Fundamentals | C2421: =Return!Q1211 -> -0.0036532386
A2422: =Return!A2 -> 46080 | B2422: Portfolio 3 - Markowitz | C2422: =Return!R2 -> -0.015965014
A2423: =Return!A3 -> 46079 | B2423: Portfolio 3 - Markowitz | C2423: =Return!R3 -> 0.01159166
A2424: =Return!A4 -> 46078 | B2424: Portfolio 3 - Markowitz | C2424: =Return!R4 -> 0.015724575
A2425: =Return!A5 -> 46077 | B2425: Portfolio 3 - Markowitz | C2425: =Return!R5 -> 0.00055071234
A2426: =Return!A6 -> 46076 | B2426: Portfolio 3 - Markowitz | C2426: =Return!R6 -> 0.0086659228
A2427: =Return!A7 -> 46073 | B2427: Portfolio 3 - Markowitz | C2427: =Return!R7 -> 0.0017615928
A2428: =Return!A8 -> 46072 | B2428: Portfolio 3 - Markowitz | C2428: =Return!R8 -> -0.0060508028
A2429: =Return!A9 -> 46071 | B2429: Portfolio 3 - Markowitz | C2429: =Return!R9 -> 0.0010160793
A2430: =Return!A10 -> 46070 | B2430: Portfolio 3 - Markowitz | C2430: =Return!R10 -> 0.003167135
A2431: =Return!A11 -> 46069 | B2431: Portfolio 3 - Markowitz | C2431: =Return!R11 -> 0.008930598
A2432: =Return!A12 -> 46066 | B2432: Portfolio 3 - Markowitz | C2432: =Return!R12 -> -0.022028215
A2433: =Return!A13 -> 46065 | B2433: Portfolio 3 - Markowitz | C2433: =Return!R13 -> 0.00019966471
... A3631: =Return!A1211 -> 44305 | B3631: Portfolio 3 - Markowitz | C3631: =Return!R1211 -> -0.0029639494
A3632: =Return!A2 -> 46080 | B3632: Portfolio 4 - SBI/Nippon Blend | C3632: =Return!S2 -> -0.0095233018
A3633: =Return!A3 -> 46079 | B3633: Portfolio 4 - SBI/Nippon Blend | C3633: =Return!S3 -> 0.0097906098
A3634: =Return!A4 -> 46078 | B3634: Portfolio 4 - SBI/Nippon Blend | C3634: =Return!S4 -> 0.014099027
A3635: =Return!A5 -> 46077 | B3635: Portfolio 4 - SBI/Nippon Blend | C3635: =Return!S5 -> 0.00017823088
A3636: =Return!A6 -> 46076 | B3636: Portfolio 4 - SBI/Nippon Blend | C3636: =Return!S6 -> 0.0071517251
A3637: =Return!A7 -> 46073 | B3637: Portfolio 4 - SBI/Nippon Blend | C3637: =Return!S7 -> -0.00099660082
A3638: =Return!A8 -> 46072 | B3638: Portfolio 4 - SBI/Nippon Blend | C3638: =Return!S8 -> -0.0057607958
A3639: =Return!A9 -> 46071 | B3639: Portfolio 4 - SBI/Nippon Blend | C3639: =Return!S9 -> 0.0025793796
A3640: =Return!A10 -> 46070 | B3640: Portfolio 4 - SBI/Nippon Blend | C3640: =Return!S10 -> 0.0057398688
A3641: =Return!A11 -> 46069 | B3641: Portfolio 4 - SBI/Nippon Blend | C3641: =Return!S11 -> 0.0061809537
A3642: =Return!A12 -> 46066 | B3642: Portfolio 4 - SBI/Nippon Blend | C3642: =Return!S12 -> -0.0090132486
A3643: =Return!A13 -> 46065 | B3643: Portfolio 4 - SBI/Nippon Blend | C3643: =Return!S13 -> -0.0046897441
... A4841: =Return!A1211 -> 44305 | B4841: Portfolio 4 - SBI/Nippon Blend | C4841: =Return!S1211 -> 0.0086287417
A4842: =Return!A2 -> 46080 | B4842: Portfolio 5 - SBI Healthcare Fund | C4842: =Return!O2 -> -0.010177489
A4843: =Return!A3 -> 46079 | B4843: Portfolio 5 - SBI Healthcare Fund | C4843: =Return!O3 -> 0.011710969
A4844: =Return!A4 -> 46078 | B4844: Portfolio 5 - SBI Healthcare Fund | C4844: =Return!O4 -> 0.014566179
A4845: =Return!A5 -> 46077 | B4845: Portfolio 5 - SBI Healthcare Fund | C4845: =Return!O5 -> 0.0027319213
A4846: =Return!A6 -> 46076 | B4846: Portfolio 5 - SBI Healthcare Fund | C4846: =Return!O6 -> 0.006126388
A4847: =Return!A7 -> 46073 | B4847: Portfolio 5 - SBI Healthcare Fund | C4847: =Return!O7 -> -0.0017318398
A4848: =Return!A8 -> 46072 | B4848: Portfolio 5 - SBI Healthcare Fund | C4848: =Return!O8 -> -0.0061605394
A4849: =Return!A9 -> 46071 | B4849: Portfolio 5 - SBI Healthcare Fund | C4849: =Return!O9 -> 0.0050751997
A4850: =Return!A10 -> 46070 | B4850: Portfolio 5 - SBI Healthcare Fund | C4850: =Return!O10 -> 0.0064350538
A4851: =Return!A11 -> 46069 | B4851: Portfolio 5 - SBI Healthcare Fund | C4851: =Return!O11 -> 0.0049656156
A4852: =Return!A12 -> 46066 | B4852: Portfolio 5 - SBI Healthcare Fund | C4852: =Return!O12 -> -0.010106899
A4853: =Return!A13 -> 46065 | B4853: Portfolio 5 - SBI Healthcare Fund | C4853: =Return!O13 -> -0.0032031894
... A6051: =Return!A1211 -> 44305 | B6051: Portfolio 5 - SBI Healthcare Fund | C6051: =Return!O1211 -> 0.0081374646
A6052: =Return!A2 -> 46080 | B6052: Portfolio 6 - Nippon Pharma Fund | C6052: =Return!P2 -> -0.0088691148
A6053: =Return!A3 -> 46079 | B6053: Portfolio 6 - Nippon Pharma Fund | C6053: =Return!P3 -> 0.0078702501
A6054: =Return!A4 -> 46078 | B6054: Portfolio 6 - Nippon Pharma Fund | C6054: =Return!P4 -> 0.013631875
A6055: =Return!A5 -> 46077 | B6055: Portfolio 6 - Nippon Pharma Fund | C6055: =Return!P5 -> -0.0023754595
A6056: =Return!A6 -> 46076 | B6056: Portfolio 6 - Nippon Pharma Fund | C6056: =Return!P6 -> 0.0081770622
A6057: =Return!A7 -> 46073 | B6057: Portfolio 6 - Nippon Pharma Fund | C6057: =Return!P7 -> -0.00026136183
A6058: =Return!A8 -> 46072 | B6058: Portfolio 6 - Nippon Pharma Fund | C6058: =Return!P8 -> -0.0053610522
A6059: =Return!A9 -> 46071 | B6059: Portfolio 6 - Nippon Pharma Fund | C6059: =Return!P9 -> 8.3559494e-05
A6060: =Return!A10 -> 46070 | B6060: Portfolio 6 - Nippon Pharma Fund | C6060: =Return!P10 -> 0.0050446837
A6061: =Return!A11 -> 46069 | B6061: Portfolio 6 - Nippon Pharma Fund | C6061: =Return!P11 -> 0.0073962917
A6062: =Return!A12 -> 46066 | B6062: Portfolio 6 - Nippon Pharma Fund | C6062: =Return!P12 -> -0.0079195986
A6063: =Return!A13 -> 46065 | B6063: Portfolio 6 - Nippon Pharma Fund | C6063: =Return!P13 -> -0.0061762989
... A7261: =Return!A1211 -> 44305 | B7261: Portfolio 6 - Nippon Pharma Fund | C7261: =Return!P1211 -> 0.0091200189

Sheet Portfolio 2 & 3
A1: Portfolio 2 (Fundamentals-Weighted) and Portfolio 3 (Markowitz-Optimal)
A3: PORTFOLIO 2: Fundamentals-Weighted
A6: Stock | B6: ROE FY26 | C6: Rev Growth FY26 | D6: Net Debt FY26 | E6: Score | F6: Weight | I6: Portfolio 2 — Performance Stats
A7: ABBOTINDIA | B7: =SUMIFS(Ratios!$F:$F,Ratios!$A:$A,"Abbott India",Ratios!$B:$B,2026)/100 -> 0.32509426 | C7: =SUMIFS(Ratios!$G:$G,Ratios!$A:$A,"Abbott India",Ratios!$B:$B,2026) -> 0.0811 | D7: =SUMIFS(Ratios!$E:$E,Ratios!$A:$A,"Abbott India",Ratios!$B:$B,2026) -> -2083 | E7: =RANK(B7,$B$7:$B$16)+RANK(C7,$C$7:$C$16)+RANK(D7,$D$7:$D$16,1) -> 11 | F7: =E7/SUM($E$7:$E$16) -> 0.066666667 | I7: Average Daily Return | J7: =AVERAGE(Return!Q2:Q1221) -> 0.00044124173
A8: ALKEM | B8: =SUMIFS(Ratios!$F:$F,Ratios!$A:$A,"Alkem Labs",Ratios!$B:$B,2026)/100 -> 0.17011577 | C8: =SUMIFS(Ratios!$G:$G,Ratios!$A:$A,"Alkem Labs",Ratios!$B:$B,2026) -> 0.1348 | D8: =SUMIFS(Ratios!$E:$E,Ratios!$A:$A,"Alkem Labs",Ratios!$B:$B,2026) -> 314 | E8: =RANK(B8,$B$7:$B$16)+RANK(C8,$C$7:$C$16)+RANK(D8,$D$7:$D$16,1) -> 16 | F8: =E8/SUM($E$7:$E$16) -> 0.096969697 | I8: Annualised Return | J8: =(1+J7)^252-1 -> 0.11758308
A9: AUROPHARMA | B9: =SUMIFS(Ratios!$F:$F,Ratios!$A:$A,"Aurobindo Pharma Ltd",Ratios!$B:$B,2026)/100 -> 0.092449394 | C9: =SUMIFS(Ratios!$G:$G,Ratios!$A:$A,"Aurobindo Pharma Ltd",Ratios!$B:$B,2026) -> 0.0608 | D9: =SUMIFS(Ratios!$E:$E,Ratios!$A:$A,"Aurobindo Pharma Ltd",Ratios!$B:$B,2026) -> -1797 | E9: =RANK(B9,$B$7:$B$16)+RANK(C9,$C$7:$C$16)+RANK(D9,$D$7:$D$16,1) -> 22 | F9: =E9/SUM($E$7:$E$16) -> 0.13333333 | I9: Daily Std Dev | J9: =STDEV(Return!Q2:Q1221) -> 0.0065605911
A10: LUPIN | B10: =SUMIFS(Ratios!$F:$F,Ratios!$A:$A,"Lupin",Ratios!$B:$B,2026)/100 -> 0.23855132 | C10: =SUMIFS(Ratios!$G:$G,Ratios!$A:$A,"Lupin",Ratios!$B:$B,2026) -> 0.2312 | D10: =SUMIFS(Ratios!$E:$E,Ratios!$A:$A,"Lupin",Ratios!$B:$B,2026) -> 963 | E10: =RANK(B10,$B$7:$B$16)+RANK(C10,$C$7:$C$16)+RANK(D10,$D$7:$D$16,1) -> 12 | F10: =E10/SUM($E$7:$E$16) -> 0.072727273 | I10: Annualised Std Dev | J10: =J9*SQRT(252) -> 0.10414616
A11: ZYDUSLIFE | B11: =SUMIFS(Ratios!$F:$F,Ratios!$A:$A,"Zydus Lifesciences Ltd",Ratios!$B:$B,2026)/100 -> 0.1889938 | C11: =SUMIFS(Ratios!$G:$G,Ratios!$A:$A,"Zydus Lifesciences Ltd",Ratios!$B:$B,2026) -> 0.1681 | D11: =SUMIFS(Ratios!$E:$E,Ratios!$A:$A,"Zydus Lifesciences Ltd",Ratios!$B:$B,2026) -> 11079 | E11: =RANK(B11,$B$7:$B$16)+RANK(C11,$C$7:$C$16)+RANK(D11,$D$7:$D$16,1) -> 17 | F11: =E11/SUM($E$7:$E$16) -> 0.1030303 | I11: Beta (vs SBI) | J11: =COVAR(Return!Q2:Q1221,Return!O2:O1221)/VAR(Return!O2:O1221) -> 0.20342873
A12: TORNTPHARM | B12: =SUMIFS(Ratios!$F:$F,Ratios!$A:$A,"Torrent Pharma",Ratios!$B:$B,2026)/100 -> 0.25488794 | C12: =SUMIFS(Ratios!$G:$G,Ratios!$A:$A,"Torrent Pharma",Ratios!$B:$B,2026) -> 0.2139 | D12: =SUMIFS(Ratios!$E:$E,Ratios!$A:$A,"Torrent Pharma",Ratios!$B:$B,2026) -> -1165 | E12: =RANK(B12,$B$7:$B$16)+RANK(C12,$C$7:$C$16)+RANK(D12,$D$7:$D$16,1) -> 9 | F12: =E12/SUM($E$7:$E$16) -> 0.054545455 | I12: Rf (assumption) | J12: ='Stock Statistics'!P18 -> 0.0682
A13: DRREDDY | B13: =SUMIFS(Ratios!$F:$F,Ratios!$A:$A,"Dr Reddy",Ratios!$B:$B,2026)/100 -> 0.10973293 | C13: =SUMIFS(Ratios!$G:$G,Ratios!$A:$A,"Dr Reddy",Ratios!$B:$B,2026) -> 0.0324 | D13: =SUMIFS(Ratios!$E:$E,Ratios!$A:$A,"Dr Reddy",Ratios!$B:$B,2026) -> 4385 | E13: =RANK(B13,$B$7:$B$16)+RANK(C13,$C$7:$C$16)+RANK(D13,$D$7:$D$16,1) -> 27 | F13: =E13/SUM($E$7:$E$16) -> 0.16363636 | I13: Rm - SBI | J13: ='Stock Statistics'!P19 -> 0.18001297
A14: SUNPHARMA | B14: =SUMIFS(Ratios!$F:$F,Ratios!$A:$A,"Sun Pharmaceutical",Ratios!$B:$B,2026)/100 -> 0.13771688 | C14: =SUMIFS(Ratios!$G:$G,Ratios!$A:$A,"Sun Pharmaceutical",Ratios!$B:$B,2026) -> 0.1119 | D14: =SUMIFS(Ratios!$E:$E,Ratios!$A:$A,"Sun Pharmaceutical",Ratios!$B:$B,2026) -> -6976 | E14: =RANK(B14,$B$7:$B$16)+RANK(C14,$C$7:$C$16)+RANK(D14,$D$7:$D$16,1) -> 14 | F14: =E14/SUM($E$7:$E$16) -> 0.084848485 | I14: Jensen's Alpha | J14: =J8-(J12+J11*(J13-J12)) -> 0.02663711
A15: CIPLA | B15: =SUMIFS(Ratios!$F:$F,Ratios!$A:$A,"Cipla",Ratios!$B:$B,2026)/100 -> 0.1121631 | C15: =SUMIFS(Ratios!$G:$G,Ratios!$A:$A,"Cipla",Ratios!$B:$B,2026) -> 0.0223 | D15: =SUMIFS(Ratios!$E:$E,Ratios!$A:$A,"Cipla",Ratios!$B:$B,2026) -> -693 | E15: =RANK(B15,$B$7:$B$16)+RANK(C15,$C$7:$C$16)+RANK(D15,$D$7:$D$16,1) -> 24 | F15: =E15/SUM($E$7:$E$16) -> 0.14545455 | I15: Sharpe Ratio | J15: =(J8-J12)/J10 -> 0.47417095
A16: DIVISLAB | B16: =SUMIFS(Ratios!$F:$F,Ratios!$A:$A,"Divi's Laboratories",Ratios!$B:$B,2026)/100 -> 0.15321282 | C16: =SUMIFS(Ratios!$G:$G,Ratios!$A:$A,"Divi's Laboratories",Ratios!$B:$B,2026) -> 0.1282 | D16: =SUMIFS(Ratios!$E:$E,Ratios!$A:$A,"Divi's Laboratories",Ratios!$B:$B,2026) -> -3407 | E16: =RANK(B16,$B$7:$B$16)+RANK(C16,$C$7:$C$16)+RANK(D16,$D$7:$D$16,1) -> 13 | F16: =E16/SUM($E$7:$E$16) -> 0.078787879 | I16: Treynor Ratio | J16: =(J8-J12)/J11 -> 0.24275372
A17: Total | F17: =SUM(F7:F16) -> 1
A19: PORTFOLIO 3: Markowitz Mean-Variance Optimal (Max Sharpe)
A22: Stock | B22: Weight | D22: Portfolio 3 — Performance Stats
A23: ABBOTINDIA | B23: 0.1338 | D23: Average Daily Return | E23: =AVERAGE(Return!R2:R1221) -> 0.00070281231
A24: ALKEM | B24: 0.1912 | D24: Annualised Return | E24: =(1+E23)^252-1 -> 0.19368659
A25: AUROPHARMA | B25: 0.0124 | D25: Daily Std Dev | E25: =STDEV(Return!R2:R1221) -> 0.0069527739
A26: LUPIN | B26: 0 | D26: Annualised Std Dev | E26: =E25*SQRT(252) -> 0.11037186
A27: ZYDUSLIFE | B27: 0.1577 | D27: Beta (vs SBI) | E27: =COVAR(Return!R2:R1221,Return!O2:O1221)/VAR(Return!O2:O1221) -> 0.16794586
A28: TORNTPHARM | B28: 0.1062 | D28: Rf (assumption) | E28: ='Stock Statistics'!P18 -> 0.0682
A29: DRREDDY | B29: 0.03 | D29: Rm - SBI | E29: ='Stock Statistics'!P19 -> 0.18001297
A30: SUNPHARMA | B30: 0.25 | D30: Jensen's Alpha | E30: =E24-(E28+E27*(E29-E28)) -> 0.10670806
A31: CIPLA | B31: 0.0329 | D31: Sharpe Ratio | E31: =(E24-E28)/E26 -> 1.1369437
A32: DIVISLAB | B32: 0.0859 | D32: Treynor Ratio | E32: =(E24-E28)/E27 -> 0.74718478
A33: Total | B33: =SUM(B23:B32) -> 1.0001

Sheet Portfolio 4-6
A1: Portfolio 4 (SBI/Nippon Blend), Portfolio 5 (SBI Fund), Portfolio 6 (Nippon Fund)
A3: PORTFOLIO 4: Benchmark Blend (50% SBI Healthcare + 50% Nippon India Pharma)
A6: Average Daily Return | B6: =AVERAGE(Return!S2:S1221) -> 0.00069905593 | D6: Average Daily Return | E6: =AVERAGE(Return!O2:O1221) -> 0.00072144177 | G6: Average Daily Return | H6: =AVERAGE(Return!P2:P1221) -> 0.00066056214
A7: Annualised Return | B7: =(1+B6)^252-1 -> 0.19255796 | D7: Annualised Return | E7: =(1+E6)^252-1 -> 0.19929967 | G7: Annualised Return | H7: =(1+H6)^252-1 -> 0.18105334
A8: Daily Std Dev | B8: =STDEV(Return!S2:S1221) -> 0.0059932691 | D8: Daily Std Dev | E8: =STDEV(Return!O2:O1221) -> 0.0082266777 | G8: Daily Std Dev | H8: =STDEV(Return!P2:P1221) -> 0.0083578425
A9: Annualised Std Dev | B9: =B8*SQRT(252) -> 0.095140197 | D9: Annualised Std Dev | E9: =E8*SQRT(252) -> 0.13059446 | G9: Annualised Std Dev | H9: =H8*SQRT(252) -> 0.13267664
A10: Beta (vs SBI) | B10: =COVAR(Return!S2:S1221,Return!O2:O1221)/VAR(Return!O2:O1221) -> 0.52146352 | D10: Beta (vs SBI) | E10: =COVAR(Return!O2:O1221,Return!O2:O1221)/VAR(Return!O2:O1221) -> 0.99917831 | G10: Beta (vs SBI) | H10: =COVAR(Return!P2:P1221,Return!O2:O1221)/VAR(Return!O2:O1221) -> 0.034792532
A11: Rf (assumption) | B11: ='Stock Statistics'!P18 -> 0.0682 | D11: Rf (assumption) | E11: ='Stock Statistics'!P18 -> 0.0682 | G11: Rf (assumption) | H11: ='Stock Statistics'!P18 -> 0.0682
A12: Rm - SBI | B12: ='Stock Statistics'!P19 -> 0.18001297 | D12: Rm - SBI | E12: ='Stock Statistics'!P19 -> 0.18001297 | G12: Rm - SBI | H12: ='Stock Statistics'!P19 -> 0.18001297
A13: Jensen's Alpha | B13: =B7-(B11+B10*(B12-B11)) -> 0.066051578 | D13: Jensen's Alpha | E13: =E7-(E11+E10*(E12-E11)) -> 0.019378572 | G13: Jensen's Alpha | H13: =H7-(H11+H10*(H12-H11)) -> 0.10896309
A14: Sharpe Ratio | B14: =(B7-B11)/B9 -> 1.3071022 | D14: Sharpe Ratio | E14: =(E7-E11)/E9 -> 1.0038685 | G14: Sharpe Ratio | H14: =(H7-H11)/H9 -> 0.85058942
A15: Treynor Ratio | B15: =(B7-B11)/B10 -> 0.23847874 | D15: Treynor Ratio | E15: =(E7-E11)/E10 -> 0.13120748 | G15: Treynor Ratio | H15: =(H7-H11)/H10 -> 3.2436083

Sheet Torrent Pharma
A1: Torrent Pharma
B2: 44621 | C2: 44986 | D2: 45352 | E2: 45717 | F2: 46082
A3: Sales - | B3: 8508 | C3: 9620 | D3: 10728 | E3: 11516 | F3: 13980
A4: Sales Growth % | B4: 0.0629 | C4: 0.1307 | D4: 0.1151 | E4: 0.0735 | F4: 0.2139
A5: Expenses - | B5: 6077 | C5: 6778 | D5: 7360 | E5: 7795 | F5: 9421
A6: Material Cost % - | B6: 0.287 | C6: 0.2843 | D6: 0.2504 | E6: 0.241 | F6: 0.2424
A7: Raw material cost | B7: 2368 | C7: 2569 | D7: 2841 | E7: 3051 | F7: 3377
A8: Change in inventory | B8: 74 | C8: 166 | D8: -155 | E8: -275 | F8: 11
A9: Manufacturing Cost % | B9: 0.0386 | C9: 0.0345 | D9: 0.0319 | E9: 0.0306 | F9: 0.031
A10: Employee Cost % | B10: 0.1795 | C10: 0.1747 | D10: 0.1852 | E10: 0.1915 | F10: 0.1912
A11: Other Cost % | B11: 0.2091 | C11: 0.211 | D11: 0.2185 | E11: 0.2137 | F11: 0.2093
A12: Operating Profit | B12: 2431 | C12: 2842 | D12: 3368 | E12: 3721 | F12: 4558
A13: OPM % | B13: 0.29 | C13: 0.3 | D13: 0.31 | E13: 0.32 | F13: 0.33
A14: Other Income - | B14: -288 | C14: 45 | D14: 146 | E14: -1 | F14: -182
... A29: Dividend Payout % | B29: 1.05 | C29: 0.6 | D29: 0.57 | E29: 0.57 | F29: 0.59
A31: BALANCE SHEET
B32: 44621 | C32: 44986 | D32: 45352 | E32: 45717 | F32: 46082
A33: Equity Capital | B33: 85 | C33: 169 | D33: 169 | E33: 169 | F33: 169
A34: Reserves | B34: 5868 | C34: 6029 | D34: 6687 | E34: 7421 | F34: 8219
A35: Borrowings - | B35: 4070 | C35: 5369 | D35: 4022 | E35: 3202 | F35: 15026
A36: Long term Borrowings | B36: 2123 | C36: 2496 | D36: 1604 | E36: 1192 | F36: 11651
A37: Short term Borrowings | B37: 1895 | C37: 2801 | D37: 2334 | E37: 1834 | F37: 3147
A38: Lease Liabilities | B38: 52 | C38: 71 | D38: 85 | E38: 176 | F38: 227
A39: Other Borrowings | B39: 0 | C39: 0 | D39: 0 | E39: 0 | F39: 0
A40: Other Liabilities - | B40: 2884 | C40: 3043 | D40: 3627 | E40: 3603 | F40: 20200
A41: Non controlling int | B41: 0 | C41: 0 | D41: 0 | E41: 0 | F41: 9196
A42: Trade Payables | B42: 1674 | C42: 1679 | D42: 2089 | E42: 1820 | F42: 2358
A43: Advance from Customers | B43: 10 | C43: 1 | D43: 4 | E43: 2 | F43: 27
A44: Other liability items | B44: 1199 | C44: 1363 | D44: 1534 | E44: 1781 | F44: 8618
... A66: Total Assets | B66: 12906 | C66: 14610 | D66: 14505 | E66: 14396 | F66: 43614
A68: CASH FLOW STATEMENT
A69: YEAR | B69: 44621 | C69: 44986 | D69: 45352 | E69: 45717 | F69: 46082
A70: Cash from Operating Activity - | B70: 1803 | C70: 2368 | D70: 3266 | E70: 2585 | F70: 3023
A71: Profit from operations | B71: 2576 | C71: 2784 | D71: 3346 | E71: 3669 | F71: 4174
A72: Receivables | B72: -113 | C72: -290 | D72: 78 | E72: 17 | F72: -254
A73: Inventory | B73: 219 | C73: 256 | D73: -49 | E73: -262 | F73: 34
A74: Payables | B74: -458 | C74: -58 | D74: 414 | E74: -278 | F74: 164
A75: Loans Advances | B75: 0 | C75: -19 | D75: -7 | E75: -52 | F75: -109
A76: Other WC items | B76: 0 | C76: 93 | D76: -18 | E76: 94 | F76: -178
A77: Working capital changes | B77: -352 | C77: -18 | D77: 418 | E77: -481 | F77: -342
A78: Direct taxes | B78: -421 | C78: -398 | D78: -498 | E78: -603 | F78: -809
A79: Cash from Investing Activity - | B79: -196 | C79: -2335 | D79: -160 | E79: -549 | F79: -12630
A80: Fixed assets purchased | B80: -203 | C80: -574 | D80: -433 | E80: -612 | F80: -677
... A97: CFO/OP | B97: 0.91 | C97: 0.97 | D97: 1.12 | E97: 0.86 | F97: 0.84

Sheet Alkem Labs
A1: Alkem Labs
B2: 44621 | C2: 44986 | D2: 45352 | E2: 45717 | F2: 46082
A3: Sales - | B3: 10634 | C3: 11599 | D3: 12668 | E3: 12965 | F3: 14712
A4: Sales Growth % | B4: 0.1996 | C4: 0.0908 | D4: 0.0921 | E4: 0.0234 | F4: 0.1348
A5: Expenses - | B5: 8580 | C5: 9977 | D5: 10419 | E5: 10452 | F5: 11706
A6: Material Cost % + | B6: 0.3931 | C6: 0.423 | D6: 0.3898 | E6: 0.3675 | F6: 0.3462
A7: Manufacturing Cost % | B7: 0.0489 | C7: 0.0442 | D7: 0.0434 | E7: 0.0612 | F7: 0.0536
A8: Employee Cost % | B8: 0.1847 | C8: 0.1839 | D8: 0.1739 | E8: 0.1894 | F8: 0.193
A9: Other Cost % | B9: 0.1801 | C9: 0.209 | D9: 0.2155 | E9: 0.1882 | F9: 0.2029
A10: Operating Profit | B10: 2054 | C10: 1622 | D10: 2249 | E10: 2512 | F10: 3007
A11: OPM % | B11: 0.19 | C11: 0.14 | D11: 0.18 | E11: 0.19 | F11: 0.2
A12: Other Income - | B12: 146 | C12: 101 | D12: 186 | E12: 494 | F12: 407
A13: Exceptional items | B13: -13 | C13: -115 | D13: -125 | E13: 5 | F13: -176
A14: Other income normal | B14: 159 | C14: 216 | D14: 311 | E14: 489 | F14: 583
... A28: Dividend Payout % | B28: 0.25 | C28: 0.61 | D28: 0.27 | E28: 0.25 | F28: 0.28
B31: 44621 | C31: 44986 | D31: 45352 | E31: 45717 | F31: 46082
A32: Equity Capital | B32: 24 | C32: 24 | D32: 24 | E32: 24 | F32: 24
A33: Reserves | B33: 8614 | C33: 9021 | D33: 10288 | E33: 11961 | F33: 13796
A34: Borrowings - | B34: 2668 | C34: 1397 | D34: 1418 | E34: 1381 | F34: 2047
A35: Long term Borrowings | B35: 9 | C35: 0 | D35: 40 | E35: 311 | F35: 492
A36: Short term Borrowings | B36: 2571 | C36: 1307 | D36: 1174 | E36: 752 | F36: 1131
A37: Lease Liabilities | B37: 88 | C37: 90 | D37: 204 | E37: 318 | F37: 424
A38: Other Borrowings | B38: 0 | C38: 0 | D38: 0 | E38: 0 | F38: 0
A39: Other Liabilities - | B39: 2763 | C39: 3315 | D39: 3844 | E39: 4325 | F39: 4991
A40: Non controlling int | B40: 209 | C40: 390 | D40: 402 | E40: 449 | F40: 529
A41: Trade Payables | B41: 1173 | C41: 1165 | D41: 1748 | E41: 1937 | F41: 2244
A42: Advance from Customers | B42: 73 | C42: 74 | D42: 112 | E42: 220 | F42: 235
A43: Other liability items | B43: 1307 | C43: 1686 | D43: 1582 | E43: 1719 | F43: 1983
... A64: Total Assets | B64: 14069 | C64: 13757 | D64: 15575 | E64: 17691 | F64: 20858
B67: 44621 | C67: 44986 | D67: 45352 | E67: 45717 | F67: 46082
A68: Cash from Operating Activity - | B68: 1111 | C68: 1682 | D68: 1948 | E68: 1913 | F68: 1963
A69: Profit from operations | B69: 2053 | C69: 1629 | D69: 2407 | E69: 2631 | F69: 3007
A70: Receivables | B70: -222 | C70: -135 | D70: -222 | E70: -219 | F70: -329
A71: Inventory | B71: -673 | C71: 473 | D71: -73 | E71: -261 | F71: -247
A72: Payables | B72: 334 | C72: 15 | D72: 525 | E72: 217 | F72: 121
A73: Loans Advances | B73: -44 | C73: -77 | D73: -135 | E73: 25 | F73: -88
A74: Other WC items | B74: 59 | C74: 51 | D74: -146 | E74: 24 | F74: 127
A75: Working capital changes | B75: -545 | C75: 327 | D75: -52 | E75: -214 | F75: -415
A76: Direct taxes | B76: -397 | C76: -273 | D76: -407 | E76: -504 | F76: -629
A77: Cash from Investing Activity - | B77: -1433 | C77: 120 | D77: -1011 | E77: -1288 | F77: -1682
A78: Fixed assets purchased | B78: -339 | C78: -233 | D78: -259 | E78: -676 | F78: -617
A79: Fixed assets sold | B79: 11 | C79: 3 | D79: 72 | E79: 41 | F79: 130
... A99: CFO/OP | B99: 0.73 | C99: 1.21 | D99: 1.05 | E99: 0.96 | F99: 0.86

Sheet Abbott India
A1: Abbott India
B2: 44621 | C2: 44986 | D2: 45352 | E2: 45717 | F2: 46082
A3: Sales - | B3: 4919 | C3: 5349 | D3: 5849 | E3: 6409 | F3: 6929
A4: Sales Growth % | B4: 0.1414 | C4: 0.0873 | D4: 0.0935 | E4: 0.0958 | F4: 0.0811
A5: Expenses - | B5: 3832 | C5: 4143 | D5: 4396 | E5: 4714 | F5: 5037
A6: Material Cost % - | B6: 0.54 | C6: 0.56 | D6: 0.55 | E6: 0.55 | F6: 0.53
A7: Raw material cost | B7: 2679 | C7: 2909 | D7: 3213 | E7: 3677 | F7: 3778
A8: Change in inventory | B8: -22 | C8: 66 | D8: 8 | E8: -181 | F8: -85
A9: Manufacturing Cost % | B9: 0.02 | C9: 0.01 | D9: 0.02 | E9: 0.02 | F9: 0.02
A10: Employee Cost % | B10: 0.12 | C10: 0.11 | D10: 0.1 | E10: 0.09 | F10: 0.1
A11: Other Cost % | B11: 0.11 | C11: 0.1 | D11: 0.08 | E11: 0.07 | F11: 0.07
A12: Operating Profit | B12: 1088 | C12: 1206 | D12: 1453 | E12: 1695 | F12: 1892
A13: OPM % | B13: 0.22 | C13: 0.23 | D13: 0.25 | E13: 0.26 | F13: 0.27
A14: Other Income - | B14: 77 | C14: 154 | D14: 248 | E14: 275 | F14: 288
... A28: Dividend Payout % | B28: 0.73 | C28: 0.73 | D28: 0.73 | E28: 0.71 | F28: 0.9
B31: 44621 | C31: 44986 | D31: 45352 | E31: 45717 | F31: 46082
A32: Equity Capital | B32: 21 | C32: 21 | D32: 21 | E32: 21 | F32: 21
A33: Reserves | B33: 2799 | C33: 3167 | D33: 3678 | E33: 4212 | F33: 4753
A34: Borrowings - | B34: 152 | C34: 113 | D34: 83 | E34: 197 | F34: 172
A35: Lease Liabilities | B35: 152 | C35: 113 | D35: 83 | E35: 197 | F35: 172
A36: Other Liabilities - | B36: 1253 | C36: 1254 | D36: 1411 | E36: 1487 | F36: 1556
A37: Trade Payables | B37: 889 | C37: 892 | D37: 1003 | E37: 1058 | F37: 1107
A38: Advance from Customers | B38: 0 | C38: 0 | D38: 0 | E38: 0 | F38: 0
A39: Other liability items | B39: 363 | C39: 362 | D39: 409 | E39: 430 | F39: 449
A40: Total Liabilities | B40: 4224 | C40: 4556 | D40: 5193 | E40: 5917 | F40: 6502
A41: Fixed Assets - | B41: 271 | C41: 237 | D41: 225 | E41: 336 | F41: 331
A42: Land | B42: 0 | C42: 0 | D42: 0 | E42: 0 | F42: 3
A43: Building | B43: 183 | C43: 147 | D43: 166 | E43: 250 | F43: 224
... A60: Total Assets | B60: 4224 | C60: 4556 | D60: 5193 | E60: 5917 | F60: 6502
B63: 44621 | C63: 44986 | D63: 45352 | E63: 45717 | F63: 46082
A64: Cash from Operating Activity - | B64: 948 | C64: 893 | D64: 1213 | E64: 1012 | F64: 1319
A65: Profit from operations | B65: 1108 | C65: 1211 | D65: 1488 | E65: 1716 | F65: 1929
A66: Receivables | B66: -39 | C66: -29 | D66: -2 | E66: -63 | F66: 16
A67: Inventory | B67: 30 | C67: 39 | D67: 29 | E67: -262 | F67: -65
A68: Payables | B68: 115 | C68: -1 | D68: 96 | E68: 41 | F68: 32
A69: Loans Advances | B69: 0 | C69: 0 | D69: 0 | E69: 0 | F69: 0
A70: Other WC items | B70: 23 | C70: 14 | D70: 6 | E70: 28 | F70: -53
A71: Working capital changes | B71: 129 | C71: 23 | D71: 129 | E71: -257 | F71: -70
A72: Direct taxes | B72: -289 | C72: -341 | D72: -404 | E72: -447 | F72: -540
A73: Cash from Investing Activity - | B73: -396 | C73: -148 | D73: -416 | E73: 182 | F73: -371
A74: Fixed assets purchased | B74: -44 | C74: -34 | D74: -48 | E74: -53 | F74: -41
A75: Fixed assets sold | B75: 0 | C75: 0 | D75: 0 | E75: 1 | F75: 29
... A86: CFO/OP | B86: 1.14 | C86: 1.02 | D86: 1.11 | E86: 0.86 | F86: 0.98

Sheet Aurobindo Pharma Ltd
A1: Aurobindo Pharma Ltd
B2: 44621 | C2: 44986 | D2: 45352 | E2: 45717 | F2: 46082
A3: Sales - | B3: 23455 | C3: 24855 | D3: 29002 | E3: 31724 | F3: 33653
A4: Sales Growth % | B4: -0.0532 | C4: 0.0597 | D4: 0.1668 | E4: 0.0939 | F4: 0.0608
A5: Expenses - | B5: 19060 | C5: 21148 | D5: 23176 | E5: 25164 | F5: 26783
A6: Material Cost % + | B6: 0.4323 | C6: 0.4544 | D6: 0.4346 | E6: 0.4106 | F6: 0.4008
A7: Manufacturing Cost % | B7: 0.0718 | C7: 0.0752 | D7: 0.0679 | E7: 0.0729 | F7: 0.0769
A8: Employee Cost % | B8: 0.1472 | C8: 0.1418 | D8: 0.1353 | E8: 0.1412 | F8: 0.1543
A9: Other Cost % | B9: 0.1613 | C9: 0.1795 | D9: 0.1614 | E9: 0.1685 | F9: 0.1638
A10: Operating Profit | B10: 4396 | C10: 3707 | D10: 5826 | E10: 6560 | F10: 6870
A11: OPM % | B11: 0.19 | C11: 0.15 | D11: 0.2 | E11: 0.21 | F11: 0.2
A12: Other Income - | B12: 152 | C12: 291 | D12: 366 | E12: 613 | F12: 404
A13: Exceptional items | B13: -139 | C13: 13 | D13: -168 | E13: 25 | F13: -88
A14: Other income normal | B14: 291 | C14: 277 | D14: 534 | E14: 588 | F14: 492
... A27: Dividend Payout % | B27: 0.2 | C27: 0.23 | D27: 0.08 | E27: 0 | F27: 0.07
B30: 44621 | C30: 44986 | D30: 45352 | E30: 45717 | F30: 46082
A31: Equity Capital | B31: 59 | C31: 59 | D31: 59 | E31: 58 | F31: 58
A32: Reserves | B32: 24517 | C32: 26781 | D32: 29784 | E32: 32595 | F32: 37833
A33: Borrowings - | B33: 2851 | C33: 5286 | D33: 6648 | E33: 8263 | F33: 8073
A34: Long term Borrowings | B34: 249 | C34: 619 | D34: 2135 | E34: 1562 | F34: 803
A35: Short term Borrowings | B35: 2124 | C35: 4243 | D35: 4180 | E35: 6380 | F35: 6873
A36: Lease Liabilities | B36: 478 | C36: 425 | D36: 332 | E36: 321 | F36: 397
A37: Preference Capital | B37: 0 | C37: 0 | D37: 0 | E37: 2 | F37: 5
A38: Other Borrowings | B38: 0 | C38: 0 | D38: 0 | E38: -2 | F38: -5
A39: Other Liabilities - | B39: 6211 | C39: 7379 | D39: 8227 | E39: 8566 | F39: 12232
A40: Non controlling int | B40: -2 | C40: 12 | D40: 8 | E40: -6 | F40: -8
A41: Trade Payables | B41: 2703 | C41: 3871 | D41: 4454 | E41: 4189 | F41: 5567
A42: Advance from Customers | B42: 0 | C42: 0 | D42: 0 | E42: 0 | F42: 0
... A64: Total Assets | B64: 33638 | C64: 39505 | D64: 44717 | E64: 49482 | F64: 58196
B67: 44621 | C67: 44986 | D67: 45352 | E67: 45717 | F67: 46082
A68: Cash from Operating Activity - | B68: 5016 | C68: 2387 | D68: 2435 | E68: 3925 | F68: 5526
A69: Profit from operations | B69: 4717 | C69: 4199 | D69: 5876 | E69: 6900 | F69: 7194
A70: Receivables | B70: -411 | C70: -432 | D70: -264 | E70: -862 | F70: -1171
A71: Inventory | B71: 1498 | C71: -927 | D71: -1304 | E71: -735 | F71: -1500
A72: Payables | B72: 111 | C72: 708 | D72: 583 | E72: -311 | F72: 1282
A73: Loans Advances | B73: 3 | C73: 1 | D73: 0 | E73: 0 | F73: 0
A74: Other WC items | B74: 358 | C74: -445 | D74: -690 | E74: 664 | F74: 1553
A75: Working capital changes | B75: 1558 | C75: -1095 | D75: -1675 | E75: -1244 | F75: 164
A76: Direct taxes | B76: -1258 | C76: -717 | D76: -1767 | E76: -1731 | F76: -1832
A77: Cash from Investing Activity - | B77: -3211 | C77: -3971 | D77: -4242 | E77: -1866 | F77: -2630
A78: Fixed assets purchased | B78: -2705 | C78: -2720 | D78: -3562 | E78: -2520 | F78: -3105
A79: Fixed assets sold | B79: 381 | C79: 11 | D79: 60 | E79: 3 | F79: 46
... A98: CFO/OP | B98: 1.43 | C98: 0.84 | D98: 0.72 | E98: 0.86 | F98: 1.07

Sheet Zydus Lifesciences Ltd
A1: Zydus Lifesciences Ltd
B2: 44621 | C2: 44986 | D2: 45352 | E2: 45717 | F2: 46082
A3: Sales - | B3: 15265 | C3: 17237 | D3: 19547 | E3: 23242 | F3: 27148
A4: Sales Growth % | B4: 0.0108 | C4: 0.1292 | D4: 0.134 | E4: 0.189 | F4: 0.1681
A5: Expenses - | B5: 11923 | C5: 13378 | D5: 14163 | E5: 16183 | F5: 18673
A6: Material Cost % + | B6: 0.3633 | C6: 0.3661 | D6: 0.3186 | E6: 0.2727 | F6: 0.2686
A7: Manufacturing Cost % | B7: 0.0532 | C7: 0.0484 | D7: 0.0467 | E7: 0.0422 | F7: 0.0416
A8: Employee Cost % | B8: 0.1597 | C8: 0.1607 | D8: 0.1607 | E8: 0.1586 | F8: 0.1629
A9: Other Cost % | B9: 0.2049 | C9: 0.201 | D9: 0.1985 | E9: 0.2228 | F9: 0.2148
A10: Operating Profit | B10: 3342 | C10: 3860 | D10: 5384 | E10: 7058 | F10: 8475
A11: OPM % | B11: 0.22 | C11: 0.22 | D11: 0.28 | E11: 0.3 | F11: 0.31
A12: Other Income - | B12: 2581 | C12: -422 | D12: 293 | E12: 50 | F12: -7
A13: Exceptional items | B13: 2357 | C13: -588 | D13: 22 | E13: -185 | F13: -514
A14: Other income normal | B14: 225 | C14: 166 | D14: 271 | E14: 235 | F14: 507
... A28: Dividend Payout % | B28: 0.06 | C28: 0.31 | D28: 0.08 | E28: 0.24 | F28: 0.02
B31: 44621 | C31: 44986 | D31: 45352 | E31: 45717 | F31: 46082
A32: Equity Capital | B32: 102 | C32: 101 | D32: 101 | E32: 101 | F32: 101
A33: Reserves | B33: 16897 | C33: 17415 | D33: 19729 | E33: 23852 | F33: 27011
A34: Borrowings - | B34: 4221 | C34: 1195 | D34: 804 | E34: 3213 | F34: 12496
A35: Long term Borrowings | B35: 362 | C35: 0 | D35: 0 | E35: 0 | F35: 3188
A36: Short term Borrowings | B36: 3834 | C36: 1163 | D36: 769 | E36: 3170 | F36: 8582
A37: Lease Liabilities | B37: 25 | C37: 32 | D37: 36 | E37: 44 | F37: 726
A38: Other Borrowings | B38: 0 | C38: 0 | D38: 0 | E38: 0 | F38: 0
A39: Other Liabilities - | B39: 6421 | C39: 6851 | D39: 8201 | E39: 9523 | F39: 11065
A40: Non controlling int | B40: 2054 | C40: 2172 | D40: 2272 | E40: 2405 | F40: 2471
A41: Trade Payables | B41: 2138 | C41: 2125 | D41: 2127 | E41: 2281 | F41: 2845
A42: Advance from Customers | B42: 49 | C42: 72 | D42: 73 | E42: 73 | F42: 82
A43: Other liability items | B43: 2180 | C43: 2482 | D43: 3729 | E43: 4764 | F43: 5667
... A64: Total Assets | B64: 27642 | C64: 25562 | D64: 28834 | E64: 36689 | F64: 50673
B67: 44621 | C67: 44986 | D67: 45352 | E67: 45717 | F67: 46082
A68: Cash from Operating Activity - | B68: 2104 | C68: 2689 | D68: 3228 | E68: 6781 | F68: 2117
A69: Profit from operations | B69: 3130 | C69: 3517 | D69: 5385 | E69: 7047 | F69: 6331
A70: Receivables | B70: -182 | C70: -848 | D70: -747 | E70: 1196 | F70: -858
A71: Inventory | B71: -526 | C71: 441 | D71: -2 | E71: -445 | F71: -412
A72: Payables | B72: -120 | C72: -171 | D72: -45 | E72: 74 | F72: -795
A73: Loans Advances | B73: 0 | C73: 0 | D73: 0 | E73: 0 | F73: 0
A74: Other WC items | B74: 476 | C74: 343 | D74: -77 | E74: 712 | F74: -558
A75: Working capital changes | B75: -352 | C75: -236 | D75: -871 | E75: 1536 | F75: -2624
A76: Direct taxes | B76: -675 | C76: -592 | D76: -1286 | E76: -1802 | F76: -1591
A77: Other operating items | B77: 0 | C77: 0 | D77: 0 | E77: 0 | F77: 0
A78: Exceptional CF items | B78: 0 | C78: 0 | D78: 0 | E78: 0 | F78: 0
A79: Cash from Investing Activity - | B79: 1137 | C79: 1178 | D79: -1492 | E79: -8363 | F79: -7895
... A99: CFO/OP | B99: 0.83 | C99: 0.85 | D99: 0.84 | E99: 1.22 | F99: 0.44

Sheet Lupin
A1: Lupin
B2: 44621 | C2: 44986 | D2: 45352 | E2: 45717 | F2: 46082
A3: Sales - | B3: 16405 | C3: 16642 | D3: 20011 | E3: 22708 | F3: 27958
A4: Sales Growth % | B4: 0.0819 | C4: 0.0144 | D4: 0.2025 | E4: 0.1348 | F4: 0.2312
A5: Expenses - | B5: 16187 | C5: 14921 | D5: 16211 | E5: 17430 | F5: 19798
A6: Material Cost % + | B6: 0.3951 | C6: 0.4074 | D6: 0.332 | E6: 0.3013 | F6: 0.2621
A7: Manufacturing Cost % | B7: 0.1177 | C7: 0.1142 | D7: 0.1116 | E7: 0.1084 | F7: 0.1003
A8: Employee Cost % | B8: 0.1822 | C8: 0.1855 | D8: 0.1746 | E8: 0.1746 | F8: 0.1636
A9: Other Cost % | B9: 0.2916 | C9: 0.1895 | D9: 0.1919 | E9: 0.1833 | F9: 0.1822
A10: Operating Profit | B10: 219 | C10: 1721 | D10: 3800 | E10: 5278 | F10: 8160
A11: OPM % | B11: 0.013 | C11: 0.1 | D11: 0.19 | E11: 0.23 | F11: 0.29
A12: Other Income - | B12: 210 | C12: 151 | D12: 131 | E12: 202 | F12: 523
A13: Exceptional items | B13: 33 | C13: 33 | D13: 31 | E13: 45 | F13: -456
A14: Other income normal | B14: 177 | C14: 118 | D14: 100 | E14: 156 | F14: 979
... A28: Dividend Payout % | B28: -0.12 | C28: 0.42 | D28: 0.19 | E28: 0.17 | F28: 0.15
B31: 44621 | C31: 44986 | D31: 45352 | E31: 45717 | F31: 46082
A32: Equity Capital | B32: 91 | C32: 91 | D32: 91 | E32: 91 | F32: 91
A33: Reserves | B33: 12062 | C33: 12374 | D33: 14199 | E33: 17112 | F33: 22357
A34: Borrowings - | B34: 4158 | C34: 4542 | D34: 2922 | E34: 5448 | F34: 6616
A35: Long term Borrowings | B35: 142 | C35: 28 | D35: 0 | E35: 1766 | F35: 1643
A36: Short term Borrowings | B36: 3702 | C36: 4217 | D36: 2670 | E36: 3310 | F36: 4267
A37: Lease Liabilities | B37: 314 | C37: 297 | D37: 252 | E37: 371 | F37: 706
A38: Other Borrowings | B38: 0 | C38: 0 | D38: 0 | E38: 0 | F38: 0
A39: Other Liabilities - | B39: 5340 | C39: 5794 | D39: 6539 | E39: 6327 | F39: 9082
A40: Non controlling int | B40: 69 | C40: 78 | D40: 83 | E40: 91 | F40: 65
A41: Trade Payables | B41: 2283 | C41: 2532 | D41: 2958 | E41: 2958 | F41: 4173
A42: Advance from Customers | B42: 16 | C42: 15 | D42: 25 | E42: 22 | F42: 21
A43: Other liability items | B43: 2973 | C43: 3169 | D43: 3473 | E43: 3257 | F43: 4822
... A64: Total Assets | B64: 21651 | C64: 22800 | D64: 23751 | E64: 28978 | F64: 38146
B67: 44621 | C67: 44986 | D67: 45352 | E67: 45717 | F67: 46082
A68: Cash from Operating Activity - | B68: 367 | C68: 1897 | D68: 3648 | E68: 3000 | F68: 7334
A69: Profit from operations | B69: 335 | C69: 1814 | D69: 3889 | E69: 5317 | F69: 7968
A70: Receivables | B70: 275 | C70: -132 | D70: -241 | E70: -781 | F70: -739
A71: Inventory | B71: -499 | C71: 195 | D71: -440 | E71: -541 | F71: -586
A72: Payables | B72: 234 | C72: 217 | D72: 419 | E72: 1 | F72: 1191
A73: Loans Advances | B73: 3 | C73: -15 | D73: 0 | E73: 0 | F73: 0
A74: Other WC items | B74: -28 | C74: 62 | D74: 348 | E74: -89 | F74: 768
A75: Working capital changes | B75: -15 | C75: 327 | D75: 86 | E75: -1411 | F75: 634
A76: Direct taxes | B76: 47 | C76: -243 | D76: -326 | E76: -906 | F76: -1267
A77: Cash from Investing Activity - | B77: 1292 | C77: -1287 | D77: -1712 | E77: -4172 | F77: -3865
A78: Fixed assets purchased | B78: -905 | C78: -1500 | D78: -929 | E78: -1682 | F78: -2055
A79: Fixed assets sold | B79: 7 | C79: 39 | D79: 12 | E79: 29 | F79: 248
... A97: CFO/OP | B97: 1.46 | C97: 1.24 | D97: 1.05 | E97: 0.74 | F97: 1.05

Sheet Sun Pharmaceutical 
A1: Sun Pharmaceutical
A2: Profit & Loss
B3: 44621 | C3: 44986 | D3: 45352 | E3: 45717 | F3: 46082
A4: Sales - | B4: 38654 | C4: 43886 | D4: 48497 | E4: 52578 | F4: 58462
A5: Sales Growth % | B5: 0.1539 | C5: 0.1353 | D5: 0.1051 | E5: 0.0842 | F5: 0.1119
A6: Expenses - | B6: 28397 | C6: 32235 | D6: 35479 | E6: 37464 | F6: 41961
A7: Material Cost % - | B7: 0.2678 | C7: 0.243 | D7: 0.2199 | E7: 0.2044 | F7: 0.1975
A8: Raw material cost | B8: 10459 | C8: 11349 | D8: 10370 | E8: 10597 | F8: 11201
A9: Change in inventory | B9: -108 | C9: -687 | D9: 292 | E9: 150 | F9: 343
A10: Manufacturing Cost % | B10: 0.0668 | C10: 0.063 | D10: 0.0608 | E10: 0.0573 | F10: 0.0578
A11: Employee Cost % | B11: 0.1889 | C11: 0.189 | D11: 0.1944 | E11: 0.1897 | F11: 0.1953
A12: Other Cost % | B12: 0.2111 | C12: 0.2395 | D12: 0.2565 | E12: 0.2612 | F12: 0.2672
A13: Operating Profit | B13: 10258 | C13: 11650 | D13: 13018 | E13: 15114 | F13: 16501
A14: OPM % | B14: 0.27 | C14: 0.27 | D14: 0.27 | E14: 0.29 | F14: 0.28
A15: Other Income - | B15: -3505 | C15: 459 | D15: 865 | E15: 1444 | F15: 1895
... A31: Dividend Payout % | B31: 0.73 | C31: 0.33 | D31: 0.34 | E31: 0.35 | F31: 0.33
A33: Balance Sheet
B34: 44621 | C34: 44986 | D34: 45352 | E34: 45717 | F34: 46082
A35: Equity Capital | B35: 240 | C35: 240 | D35: 240 | E35: 240 | F35: 240
A36: Reserves | B36: 47771 | C36: 55755 | D36: 63427 | E36: 71978 | F36: 83330
A37: Borrowings - | B37: 1290 | C37: 6886 | D37: 3274 | E37: 2362 | F37: 4627
A38: Long term Borrowings | B38: 230 | C38: 0 | D38: 1 | E38: 3 | F38: 31
A39: Short term Borrowings | B39: 701 | C39: 6198 | D39: 2844 | E39: 1867 | F39: 4050
A40: Lease Liabilities | B40: 360 | C40: 688 | D40: 428 | E40: 493 | F40: 546
A41: Other Borrowings | B41: 0 | C41: 0 | D41: 0 | E41: 0 | F41: 0
A42: Other Liabilities - | B42: 20474 | C42: 17831 | D42: 18387 | E42: 17328 | F42: 20210
A43: Non controlling int | B43: 3055 | C43: 3320 | D43: 3459 | E43: 268 | F43: 310
A44: Trade Payables | B44: 4490 | C44: 5682 | D44: 5653 | E44: 6184 | F44: 7334
A45: Advance from Customers | B45: 29 | C45: 41 | D45: 43 | E45: 25 | F45: 137
A46: Other liability items | B46: 12901 | C46: 8788 | D46: 9232 | E46: 10851 | F46: 12429
... A67: Total Assets | B67: 69776 | C67: 80712 | D67: 85328 | E67: 91908 | F67: 108407
A69: Cash flow
B70: 44621 | C70: 44986 | D70: 45352 | E70: 45717 | F70: 46082
A71: Cash from Operating Activity - | B71: 8985 | C71: 4959 | D71: 12135 | E71: 14072 | F71: 12419
A72: Profit from operations | B72: 6456 | C72: 12131 | D72: 12642 | E72: 14872 | F72: 16001
A73: Receivables | B73: -1342 | C73: -953 | D73: 353 | E73: -1602 | F73: -2009
A74: Inventory | B74: 307 | C74: -1202 | D74: 599 | E74: -184 | F74: -52
A75: Payables | B75: 370 | C75: 1182 | D75: 250 | E75: 528 | F75: 1057
A76: Loans Advances | B76: 0 | C76: 0 | D76: 0 | E76: 0 | F76: 0
A77: Other WC items | B77: 2224 | C77: -4689 | D77: -139 | E77: 934 | F77: -264
A78: Working capital changes | B78: 1559 | C78: -5662 | D78: 1062 | E78: -324 | F78: -1268
A79: Direct taxes | B79: 969 | C79: -1510 | D79: -1569 | E79: -477 | F79: -2314
A80: Cash from Investing Activity - | B80: -5556 | C80: -7220 | D80: -763 | E80: -5183 | F80: -10405
A81: Fixed assets purchased | B81: -1495 | C81: -2086 | D81: -2202 | E81: -2129 | F81: -3609
A82: Fixed assets sold | B82: 61 | C82: 21 | D82: 31 | E82: 61 | F82: 96
... A101: CFO/OP | B101: 0.78 | C101: 0.56 | D101: 1.05 | E101: 0.96 | F101: 0.89

Sheet Dr Reddy
A1: Dr Reddy
A2: Profit & Loss
B3: 44621 | C3: 44986 | D3: 45352 | E3: 45717 | F3: 46082
A4: Sales - | B4: 21545 | C4: 24670 | D4: 28011 | E4: 32644 | F4: 33700
A5: Sales Growth % | B5: 0.1311 | C5: 0.145 | D5: 0.1354 | E5: 0.1654 | F5: 0.0324
A6: Expenses - | B6: 17778 | C6: 18200 | D6: 20078 | E6: 24097 | F6: 27247
A7: Material Cost % + | B7: 0.3454 | C7: 0.3104 | D7: 0.2931 | E7: 0.3057 | F7: 0.3632
A8: Manufacturing Cost % | B8: 0.0925 | C8: 0.0898 | D8: 0.0936 | E8: 0.0958 | F8: 0.0831
A9: Employee Cost % | B9: 0.1809 | C9: 0.1888 | D9: 0.1801 | E9: 0.1714 | F9: 0.1782
A10: Other Cost % | B10: 0.2063 | C10: 0.1487 | D10: 0.1501 | E10: 0.1653 | F10: 0.184
A11: Operating Profit | B11: 3768 | C11: 6470 | D11: 7933 | E11: 8547 | F11: 6454
A12: OPM % | B12: 0.17 | C12: 0.26 | D12: 0.28 | E12: 0.26 | F12: 0.19
A13: Other Income - | B13: 555 | C13: 971 | D13: 909 | E13: 1119 | F13: 1372
A14: Exceptional items | B14: 112 | C14: -121 | D14: 90 | E14: 151 | F14: 255
A15: Other income normal | B15: 443 | C15: 1092 | D15: 819 | E15: 968 | F15: 1117
... A29: Dividend Payout % | B29: 0.23 | C29: 0.15 | D29: 0.12 | E29: 0.12 | F29: 0.16
A31: Balance Sheet
B32: 42064 | C32: 44986 | D32: 45352 | E32: 45717 | F32: 46082
A33: Equity Capital | B33: 83 | C33: 83 | D33: 83 | E33: 83 | F33: 84
A34: Reserves | B34: 19129 | C34: 23203 | D34: 28171 | E34: 33466 | F34: 37808
A35: Borrowings - | B35: 3384 | C35: 1347 | D35: 2002 | E35: 4677 | F35: 7734
A36: Long term Borrowings | B36: 380 | C36: 0 | D36: 380 | E36: 380 | F36: 0
A37: Short term Borrowings | B37: 2708 | C37: 1119 | D37: 1272 | E37: 3804 | F37: 6294
A38: Lease Liabilities | B38: 296 | C38: 228 | D38: 350 | E38: 492 | F38: 1441
A39: Other Borrowings | B39: 0 | C39: 0 | D39: 0 | E39: 0 | F39: 0
A40: Other Liabilities - | B40: 7149 | C40: 7576 | D40: 8523 | E40: 9797 | F40: 10951
A41: Non controlling int | B41: 0 | C41: 0 | D41: 0 | E41: 378 | F41: 339
A42: Trade Payables | B42: 2266 | C42: 2268 | D42: 2614 | E42: 2648 | F42: 3038
A43: Advance from Customers | B43: 134 | C43: 117 | D43: 106 | E43: 156 | F43: 132
A44: Other liability items | B44: 4748 | C44: 5190 | D44: 5802 | E44: 6615 | F44: 7442
... A65: Total Assets | B65: 29746 | C65: 32209 | D65: 38780 | E65: 48023 | F65: 56577
A67: Cash flow
B68: 42064 | C68: 44986 | D68: 45352 | E68: 45717 | F68: 46082
A69: Cash from Operating Activity - | B69: 2811 | C69: 5888 | D69: 4543 | E69: 4643 | F69: 5674
A70: Profit from operations | B70: 5395 | C70: 7744 | D70: 8566 | E70: 9641 | F70: 8101
A71: Receivables | B71: -1701 | C71: -575 | D71: -805 | E71: -1028 | F71: -672
A72: Inventory | B72: -991 | C72: -265 | D72: -1844 | E72: -1275 | F72: -860
A73: Payables | B73: 441 | C73: 2 | D73: 346 | E73: 34 | F73: 279
A74: Other WC items | B74: 410 | C74: 53 | D74: 286 | E74: -729 | F74: 179
A75: Working capital changes | B75: -1841 | C75: -786 | D75: -2018 | E75: -2999 | F75: -1075
A76: Direct taxes | B76: -744 | C76: -1071 | D76: -2005 | E76: -1999 | F76: -1353
A77: Cash from Investing Activity - | B77: -2565 | C77: -4109 | D77: -4034 | E77: -5785 | F77: -6425
A78: Fixed assets purchased | B78: -1905 | C78: -1887 | D78: -2744 | E78: -3440 | F78: -3840
A79: Fixed assets sold | B79: 332 | C79: 8 | D79: 108 | E79: 124 | F79: 171
A80: Investments purchased | B80: -8897 | C80: -13617 | D80: -14549 | E80: -2849 | F80: -4672
... A97: CFO/OP | B97: 0.94 | C97: 1.08 | D97: 0.83 | E97: 0.78 | F97: 1.09

Sheet Divis Laboratories
A1: Divis Laboratories
A2: Profit & Loss
B3: 44621 | C3: 44986 | D3: 45352 | E3: 45717 | F3: 46082
A4: Sales - | B4: 8960 | C4: 7768 | D4: 7845 | E4: 9360 | F4: 10560
A5: Sales Growth % | B5: 0.2856 | C5: -0.1331 | D5: 0.01 | E5: 0.1931 | F5: 0.1282
A6: Expenses - | B6: 5075 | C6: 5397 | D6: 5635 | E6: 6387 | F6: 7118
A7: Material Cost % + | B7: 0.338 | C7: 0.4005 | D7: 0.4068 | E7: 0.4053 | F7: 0.3952
A8: Manufacturing Cost % | B8: 0.0754 | C8: 0.1041 | D8: 0.1104 | E8: 0.0837 | F8: 0.0843
A9: Employee Cost % | B9: 0.1058 | C9: 0.1258 | D9: 0.1397 | E9: 0.133 | F9: 0.1367
A10: Other Cost % | B10: 0.0472 | C10: 0.0644 | D10: 0.0614 | E10: 0.0604 | F10: 0.0579
A11: Operating Profit | B11: 3885 | C11: 2370 | D11: 2210 | E11: 2973 | F11: 3442
A12: OPM % | B12: 0.43 | C12: 0.31 | D12: 0.28 | E12: 0.32 | F12: 0.33
A13: Other Income - | B13: 112 | C13: 344 | D13: 335 | E13: 348 | F13: 433
A14: Exceptional items | B14: -2 | C14: -1 | D14: -4 | E14: 0 | F14: -74
A15: Other income normal | B15: 114 | C15: 345 | D15: 339 | E15: 348 | F15: 507
... A27: Dividend Payout % | B27: 0.27 | C27: 0.44 | D27: 0.5 | E27: 0.36 | F27: 0.31
A29: Balance Sheet
B30: 44621 | C30: 44986 | D30: 45352 | E30: 45717 | F30: 46082
A31: Equity Capital | B31: 53 | C31: 53 | D31: 53 | E31: 53 | F31: 53
A32: Reserves | B32: 11675 | C32: 12714 | D32: 13518 | E32: 14916 | F32: 16708
A33: Borrowings - | B33: 4 | C33: 3 | D33: 3 | E33: 4 | F33: 7
A34: Long term Borrowings | B34: 0 | C34: 0 | D34: 0 | E34: 0 | F34: 0
A35: Short term Borrowings | B35: 0 | C35: 0 | D35: 0 | E35: 2 | F35: 0
A36: Lease Liabilities | B36: 3.69 | C36: 3.26 | D36: 3 | E36: 2 | F36: 7
A37: Other Borrowings | B37: 0 | C37: 0 | D37: 0 | E37: 0 | F37: 0
A38: Other Liabilities - | B38: 1628 | C38: 1654 | D38: 1886 | E38: 1948 | F38: 3251
A39: Trade Payables | B39: 796 | C39: 763 | D39: 824 | E39: 910 | F39: 1211
A40: Advance from Customers | B40: 17 | C40: 33 | D40: 34 | E40: 40 | F40: 83
A41: Other liability items | B41: 816 | C41: 859 | D41: 1028 | E41: 998 | F41: 1957
A42: Total Liabilities | B42: 13360 | C42: 14425 | D42: 15460 | E42: 16921 | F42: 20019
... A62: Total Assets | B62: 13360 | C62: 14425 | D62: 15460 | E62: 16921 | F62: 20019
A64: Cash flow
B65: 44621 | C65: 44986 | D65: 45352 | E65: 45717 | F65: 46082
A66: Cash from Operating Activity - | B66: 1912 | C66: 2460 | D66: 1261 | E66: 1653 | F66: 2738
A67: Profit from operations | B67: 3923 | C67: 2514 | D67: 2244 | E67: 3031 | F67: 3501
A68: Receivables | B68: -742 | C68: 650 | D68: -361 | E68: -582 | F68: -141
A69: Inventory | B69: -683 | C69: -172 | D69: -184 | E69: -52 | F69: -718
A70: Payables | B70: 34 | C70: -34 | D70: 62 | E70: 95 | F70: 294
A71: Loans Advances | B71: 0 | C71: 0 | D71: 0 | E71: 0 | F71: 0
A72: Other WC items | B72: 20 | C72: -26 | D72: -124 | E72: -15 | F72: 664
A73: Working capital changes | B73: -1370 | C73: 419 | D73: -607 | E73: -554 | F73: 99
A74: Direct taxes | B74: -641 | C74: -473 | D74: -376 | E74: -824 | F74: -862
A75: Cash from Investing Activity - | B75: -2195 | C75: -2708 | D75: -269 | E75: -804 | F75: -2219
A76: Fixed assets purchased | B76: -713 | C76: -473 | D76: -1003 | E76: -1438 | F76: -2520
A77: Fixed assets sold | B77: 0 | C77: 0 | D77: 0 | E77: 0 | F77: 3
... A92: CFO/OP | B92: 0.66 | C92: 1.24 | D92: 0.74 | E92: 0.83 | F92: 1.05

Sheet Cipla
A1: Cipla
A2: Profit & Loss
B3: 44621 | C3: 44986 | D3: 45352 | E3: 45717 | F3: 46082
A4: Sales - | B4: 21763 | C4: 22753 | D4: 25774 | E4: 27548 | F4: 28163
A5: Sales Growth % | B5: 0.1359 | C5: 0.0455 | D5: 0.1328 | E5: 0.0688 | F5: 0.0223
A6: Expenses - | B6: 17211 | C6: 17726 | D6: 19483 | E6: 20420 | F6: 22280
A7: Material Cost % + | B7: 0.3904 | C7: 0.3627 | D7: 0.3422 | E7: 0.3241 | F7: 0.3391
A8: Manufacturing Cost % | B8: 0.0698 | C8: 0.0685 | D8: 0.0665 | E8: 0.0695 | F8: 0.0735
A9: Employee Cost % | B9: 0.1628 | C9: 0.1689 | D9: 0.1678 | E9: 0.1761 | F9: 0.1905
A10: Other Cost % | B10: 0.1679 | C10: 0.179 | D10: 0.1794 | E10: 0.1715 | F10: 0.188
A11: Operating Profit | B11: 4553 | C11: 5027 | D11: 6291 | E11: 7128 | F11: 5883
A12: OPM % | B12: 0.21 | C12: 0.22 | D12: 0.24 | E12: 0.26 | F12: 0.21
A13: Other Income - | B13: 99 | C13: 293 | D13: 552 | E13: 862 | F13: 606
A14: Exceptional items | B14: -96 | C14: -58 | D14: -122 | E14: 169 | F14: 101
A15: Other income normal | B15: 195 | C15: 351 | D15: 674 | E15: 693 | F15: 505
... A29: Dividend Payout % | B29: 0.16 | C29: 0.24 | D29: 0.25 | E29: 0.25 | F29: 0.27
A31: Balance Sheet
B32: 44621 | C32: 44986 | D32: 45352 | E32: 45717 | F32: 46082
A33: Equity Capital | B33: 161 | C33: 161 | D33: 161 | E33: 162 | F33: 162
A34: Reserves | B34: 20680 | C34: 23246 | D34: 26545 | E34: 31032 | F34: 34270
A35: Borrowings - | B35: 1056 | C35: 803 | D35: 559 | E35: 438 | F35: 614
A36: Long term Borrowings | B36: 416 | C36: 0 | D36: 0 | E36: 12 | F36: 117
A37: Short term Borrowings | B37: 408 | C37: 520 | D37: 247 | E37: 80 | F37: 140
A38: Lease Liabilities | B38: 232 | C38: 283 | D38: 312 | E38: 346 | F38: 356
A39: Other Borrowings | B39: 0 | C39: 0 | D39: 0 | E39: 0 | F39: 0
A40: Other Liabilities - | B40: 4960 | C40: 5089 | D40: 5267 | E40: 5702 | F40: 7297
A41: Non controlling int | B41: 276 | C41: 306 | D41: 96 | E41: 96 | F41: 88
A42: Trade Payables | B42: 2508 | C42: 2535 | D42: 2474 | E42: 2837 | F42: 3230
A43: Advance from Customers | B43: 74 | C43: 63 | D43: 14 | E43: 16 | F43: 0
A44: Other liability items | B44: 2102 | C44: 2186 | D44: 2683 | E44: 2752 | F44: 3979
... A66: Total Assets | B66: 26857 | C66: 29300 | D66: 32533 | E66: 37334 | F66: 42343
A68: Cash flow
B69: 44621 | C69: 44986 | D69: 45352 | E69: 45717 | F69: 46082
A70: Cash from Operating Activity - | B70: 3326 | C70: 3238 | D70: 4134 | E70: 5005 | F70: 3940
A71: Profit from operations | B71: 4643 | C71: 5099 | D71: 6537 | E71: 7339 | F71: 5751
A72: Receivables | B72: 81 | C72: -652 | D72: -907 | E72: -802 | F72: 465
A73: Inventory | B73: -621 | C73: 111 | D73: -62 | E73: -323 | F73: -642
A74: Payables | B74: 362 | C74: -18 | D74: 163 | E74: 459 | F74: 253
A75: Other WC items | B75: 0 | C75: 0 | D75: 0 | E75: 0 | F75: -301
A76: Working capital changes | B76: -177 | C76: -559 | D76: -806 | E76: -665 | F76: -225
A77: Direct taxes | B77: -1140 | C77: -1302 | D77: -1597 | E77: -1668 | F77: -1586
A78: Cash from Investing Activity - | B78: -1858 | C78: -2376 | D78: -2982 | E78: -3682 | F78: -2234
A79: Fixed assets purchased | B79: -701 | C79: -1183 | D79: -1349 | E79: -1548 | F79: -3079
A80: Fixed assets sold | B80: 20 | C80: 47 | D80: 34 | E80: 33 | F80: 68
A81: Investments purchased | B81: 0 | C81: -888 | D81: -1432 | E81: -2095 | F81: -17
... A101: CFO/OP | B101: 0.98 | C101: 0.9 | D101: 0.91 | E101: 0.94 | F101: 0.94
